{"v":"5.5.2","fr":29.9700012207031,"ip":0,"op":44.0000017921567,"w":440,"h":587,"nm":"teamAnimation_bodymovinedition","ddd":0,"assets":[],"layers":[{"ddd":0,"ind":1,"ty":4,"nm":"backgroundColor Outlines","sr":1,"ks":{"o":{"a":0,"k":100,"ix":11},"r":{"a":0,"k":0,"ix":10},"p":{"a":0,"k":[220,293.5,0],"ix":2},"a":{"a":0,"k":[220,293.5,0],"ix":1},"s":{"a":0,"k":[100,100,100],"ix":6}},"ao":0,"shapes":[{"ty":"gr","it":[{"ind":0,"ty":"sh","ix":1,"ks":{"a":0,"k":{"i":[[0,0],[0,0],[0,0],[0,0]],"o":[[0,0],[0,0],[0,0],[0,0]],"v":[[-220,293.5],[220,293.5],[220,-293.5],[-220,-293.5]],"c":true},"ix":2},"nm":"Path 1","mn":"ADBE Vector Shape - Group","hd":false},{"ind":1,"ty":"sh","ix":2,"ks":{"a":0,"k":{"i":[[0,0],[0,0],[0,0],[0,0]],"o":[[0,0],[0,0],[0,0],[0,0]],"v":[[-220,-293.5],[220,-293.5],[220,293.5],[-220,293.5]],"c":true},"ix":2},"nm":"Path 2","mn":"ADBE Vector Shape - Group","hd":false},{"ind":2,"ty":"sh","ix":3,"ks":{"a":0,"k":{"i":[[0,0],[0,0],[0,0],[0,0]],"o":[[0,0],[0,0],[0,0],[0,0]],"v":[[-220,293.5],[220,293.5],[220,-293.5],[-220,-293.5]],"c":true},"ix":2},"nm":"Path 3","mn":"ADBE Vector Shape - Group","hd":false},{"ty":"mm","mm":1,"nm":"Merge Paths 1","mn":"ADBE Vector Filter - Merge","hd":false},{"ty":"fl","c":{"a":0,"k":[0.929000016755,0.109999997008,0.141000007181,1],"ix":4},"o":{"a":0,"k":33,"ix":5},"r":1,"bm":0,"nm":"Fill 1","mn":"ADBE Vector Graphic - Fill","hd":false},{"ty":"tr","p":{"a":0,"k":[220,293.5],"ix":2},"a":{"a":0,"k":[0,0],"ix":1},"s":{"a":0,"k":[100,100],"ix":3},"r":{"a":0,"k":0,"ix":6},"o":{"a":0,"k":100,"ix":7},"sk":{"a":0,"k":0,"ix":4},"sa":{"a":0,"k":0,"ix":5},"nm":"Transform"}],"nm":"Group 1","np":5,"cix":2,"bm":0,"ix":1,"mn":"ADBE Vector Group","hd":false}],"ip":0,"op":44.0000017921567,"st":0,"bm":0},{"ddd":0,"ind":2,"ty":4,"nm":"teeth Outlines","sr":1,"ks":{"o":{"a":0,"k":100,"ix":11},"r":{"a":0,"k":0,"ix":10},"p":{"a":1,"k":[{"i":{"x":0.833,"y":0.833},"o":{"x":0.167,"y":0.167},"t":0,"s":[220,292.5,0],"to":[0,0.5,0],"ti":[0,0,0]},{"i":{"x":0.833,"y":0.833},"o":{"x":0.167,"y":0.167},"t":14,"s":[220,295.5,0],"to":[0,0,0],"ti":[0,0.5,0]},{"t":28.0000011404634,"s":[220,292.5,0]}],"ix":2},"a":{"a":0,"k":[220,293.5,0],"ix":1},"s":{"a":0,"k":[100,100,100],"ix":6}},"ao":0,"shapes":[{"ty":"gr","it":[{"ind":0,"ty":"sh","ix":1,"ks":{"a":0,"k":{"i":[[8.104,-1.691],[0.542,0.413],[-0.46,1.298],[-4.501,0.438],[-2.958,1.255],[-0.691,-2.28],[2.814,-1.38]],"o":[[-8.071,1.771],[-1.021,-0.67],[0.102,-0.411],[8.391,-0.801],[1.402,-0.595],[0.758,2.435],[-1.68,0.802]],"v":[[-1.36,4.146],[-17.054,6.578],[-18.92,0.017],[-10.481,-1.54],[16.13,-6.396],[18.622,-4.419],[16.397,-0.35]],"c":true},"ix":2},"nm":"Path 1","mn":"ADBE Vector Shape - Group","hd":false},{"ty":"fl","c":{"a":0,"k":[0.995999983245,0.995999983245,0.995999983245,1],"ix":4},"o":{"a":0,"k":100,"ix":5},"r":1,"bm":0,"nm":"Fill 1","mn":"ADBE Vector Graphic - Fill","hd":false},{"ty":"tr","p":{"a":0,"k":[369.943,312.759],"ix":2},"a":{"a":0,"k":[0,0],"ix":1},"s":{"a":0,"k":[100,100],"ix":3},"r":{"a":0,"k":0,"ix":6},"o":{"a":0,"k":100,"ix":7},"sk":{"a":0,"k":0,"ix":4},"sa":{"a":0,"k":0,"ix":5},"nm":"Transform"}],"nm":"Group 1","np":4,"cix":2,"bm":0,"ix":1,"mn":"ADBE Vector Group","hd":false}],"ip":0,"op":44.0000017921567,"st":0,"bm":0},{"ddd":0,"ind":3,"ty":4,"nm":"rightEye Outlines","sr":1,"ks":{"o":{"a":0,"k":100,"ix":11},"r":{"a":0,"k":0,"ix":10},"p":{"a":1,"k":[{"i":{"x":0.833,"y":0.833},"o":{"x":0.167,"y":0.167},"t":0,"s":[220,293.5,0],"to":[-0.833,0.417,0],"ti":[-0.167,-0.417,0]},{"i":{"x":0.833,"y":0.833},"o":{"x":0.167,"y":0.167},"t":14,"s":[215,296,0],"to":[0.167,0.417,0],"ti":[-0.833,0.417,0]},{"i":{"x":0.833,"y":0.833},"o":{"x":0.167,"y":0.167},"t":28,"s":[221,296,0],"to":[0.833,-0.417,0],"ti":[0.167,0.417,0]},{"t":44.0000017921567,"s":[220,293.5,0]}],"ix":2},"a":{"a":0,"k":[220,293.5,0],"ix":1},"s":{"a":0,"k":[100,100,100],"ix":6}},"ao":0,"shapes":[{"ty":"gr","it":[{"ind":0,"ty":"sh","ix":1,"ks":{"a":0,"k":{"i":[[1.526,1.648],[-1.612,0.316],[-0.528,-1.246]],"o":[[-1.493,-1.572],[1.001,-0.241],[0.958,2.259]],"v":[[-1.065,1.39],[-0.727,-2.797],[1.6,-1.211]],"c":true},"ix":2},"nm":"Path 1","mn":"ADBE Vector Shape - Group","hd":false},{"ty":"fl","c":{"a":0,"k":[0.757000014361,0.152999997606,0.176000004189,1],"ix":4},"o":{"a":0,"k":100,"ix":5},"r":1,"bm":0,"nm":"Fill 1","mn":"ADBE Vector Graphic - Fill","hd":false},{"ty":"tr","p":{"a":0,"k":[385.527,275.442],"ix":2},"a":{"a":0,"k":[0,0],"ix":1},"s":{"a":0,"k":[100,100],"ix":3},"r":{"a":0,"k":0,"ix":6},"o":{"a":0,"k":100,"ix":7},"sk":{"a":0,"k":0,"ix":4},"sa":{"a":0,"k":0,"ix":5},"nm":"Transform"}],"nm":"Group 1","np":4,"cix":2,"bm":0,"ix":1,"mn":"ADBE Vector Group","hd":false}],"ip":0,"op":44.0000017921567,"st":0,"bm":0},{"ddd":0,"ind":4,"ty":4,"nm":"leftEye Outlines","sr":1,"ks":{"o":{"a":0,"k":100,"ix":11},"r":{"a":0,"k":0,"ix":10},"p":{"a":0,"k":[220,293.5,0],"ix":2},"a":{"a":0,"k":[220,293.5,0],"ix":1},"s":{"a":0,"k":[100,100,100],"ix":6}},"ao":0,"shapes":[{"ty":"gr","it":[{"ind":0,"ty":"sh","ix":1,"ks":{"a":0,"k":{"i":[[1.495,1.573],[-0.246,0.795],[-0.728,-1.713]],"o":[[-0.601,-0.575],[0.718,-1.775],[0.859,2.027]],"v":[[-1.838,1.302],[-2.418,-0.933],[1.805,-1.162]],"c":true},"ix":2},"nm":"Path 1","mn":"ADBE Vector Shape - Group","hd":false},{"ty":"fl","c":{"a":0,"k":[0.995999983245,0.995999983245,0.995999983245,1],"ix":4},"o":{"a":0,"k":100,"ix":5},"r":1,"bm":0,"nm":"Fill 1","mn":"ADBE Vector Graphic - Fill","hd":false},{"ty":"tr","p":{"a":0,"k":[341.723,284.238],"ix":2},"a":{"a":0,"k":[0,0],"ix":1},"s":{"a":0,"k":[100,100],"ix":3},"r":{"a":0,"k":0,"ix":6},"o":{"a":0,"k":100,"ix":7},"sk":{"a":0,"k":0,"ix":4},"sa":{"a":0,"k":0,"ix":5},"nm":"Transform"}],"nm":"Group 1","np":4,"cix":2,"bm":0,"ix":1,"mn":"ADBE Vector Group","hd":false}],"ip":0,"op":44.0000017921567,"st":0,"bm":0},{"ddd":0,"ind":5,"ty":4,"nm":"head Outlines","sr":1,"ks":{"o":{"a":0,"k":100,"ix":11},"r":{"a":0,"k":0,"ix":10},"p":{"a":0,"k":[220,293.5,0],"ix":2},"a":{"a":0,"k":[220,293.5,0],"ix":1},"s":{"a":0,"k":[100,100,100],"ix":6}},"ao":0,"shapes":[{"ty":"gr","it":[{"ind":0,"ty":"sh","ix":1,"ks":{"a":0,"k":{"i":[[2.017,2.103],[-2.181,0.45],[-0.68,-1.605]],"o":[[-1.973,-2.003],[1.355,-0.338],[1.234,2.906]],"v":[[-1.46,1.839],[-0.897,-3.604],[2.199,-1.604]],"c":true},"ix":2},"nm":"Path 1","mn":"ADBE Vector Shape - Group","hd":false},{"ty":"fl","c":{"a":0,"k":[0.328999986836,0.250999989229,0.136999990426,1],"ix":4},"o":{"a":0,"k":100,"ix":5},"r":1,"bm":0,"nm":"Fill 1","mn":"ADBE Vector Graphic - Fill","hd":false},{"ty":"tr","p":{"a":0,"k":[385.262,275.483],"ix":2},"a":{"a":0,"k":[0,0],"ix":1},"s":{"a":0,"k":[100,100],"ix":3},"r":{"a":0,"k":0,"ix":6},"o":{"a":0,"k":100,"ix":7},"sk":{"a":0,"k":0,"ix":4},"sa":{"a":0,"k":0,"ix":5},"nm":"Transform"}],"nm":"Group 1","np":4,"cix":2,"bm":0,"ix":1,"mn":"ADBE Vector Group","hd":false},{"ty":"gr","it":[{"ind":0,"ty":"sh","ix":1,"ks":{"a":0,"k":{"i":[[1.802,1.913],[-0.289,0.964],[-0.882,-2.079]],"o":[[-0.726,-0.7],[0.851,-2.144],[1.043,2.458]],"v":[[-2.199,1.564],[-2.909,-1.146],[2.155,-1.398]],"c":true},"ix":2},"nm":"Path 1","mn":"ADBE Vector Shape - Group","hd":false},{"ty":"fl","c":{"a":0,"k":[0.328999986836,0.250999989229,0.136999990426,1],"ix":4},"o":{"a":0,"k":100,"ix":5},"r":1,"bm":0,"nm":"Fill 1","mn":"ADBE Vector Graphic - Fill","hd":false},{"ty":"tr","p":{"a":0,"k":[341.606,283.896],"ix":2},"a":{"a":0,"k":[0,0],"ix":1},"s":{"a":0,"k":[100,100],"ix":3},"r":{"a":0,"k":0,"ix":6},"o":{"a":0,"k":100,"ix":7},"sk":{"a":0,"k":0,"ix":4},"sa":{"a":0,"k":0,"ix":5},"nm":"Transform"}],"nm":"Group 2","np":4,"cix":2,"bm":0,"ix":2,"mn":"ADBE Vector Group","hd":false},{"ty":"gr","it":[{"ind":0,"ty":"sh","ix":1,"ks":{"a":0,"k":{"i":[[4.933,-0.071],[-5.1,3.358],[-4.466,-0.127],[5.104,-4.647]],"o":[[-6.533,0.198],[5.924,-3.8],[3.977,0.059],[-3.457,3.121]],"v":[[-3.426,3.907],[-5.156,0.046],[6.279,-3.978],[5.118,0.65]],"c":true},"ix":2},"nm":"Path 1","mn":"ADBE Vector Shape - Group","hd":false},{"ty":"fl","c":{"a":0,"k":[0.944999964097,0.352999997606,0.141000007181,1],"ix":4},"o":{"a":0,"k":100,"ix":5},"r":1,"bm":0,"nm":"Fill 1","mn":"ADBE Vector Graphic - Fill","hd":false},{"ty":"tr","p":{"a":0,"k":[322.798,257.321],"ix":2},"a":{"a":0,"k":[0,0],"ix":1},"s":{"a":0,"k":[100,100],"ix":3},"r":{"a":0,"k":0,"ix":6},"o":{"a":0,"k":100,"ix":7},"sk":{"a":0,"k":0,"ix":4},"sa":{"a":0,"k":0,"ix":5},"nm":"Transform"}],"nm":"Group 3","np":4,"cix":2,"bm":0,"ix":3,"mn":"ADBE Vector Group","hd":false},{"ty":"gr","it":[{"ind":0,"ty":"sh","ix":1,"ks":{"a":0,"k":{"i":[[8.427,-1.865],[0.61,0.476],[-0.376,1.478],[-4.724,0.465],[-3.024,1.409],[-0.925,-2.608],[2.86,-1.552]],"o":[[-8.385,1.954],[-1.134,-0.774],[0.072,-0.469],[8.804,-0.847],[1.431,-0.668],[1.009,2.787],[-1.71,0.905]],"v":[[-1.057,4.721],[-17.449,7.367],[-19.98,-0.139],[-11.188,-1.849],[16.543,-7.175],[19.346,-4.9],[17.339,-0.272]],"c":true},"ix":2},"nm":"Path 1","mn":"ADBE Vector Shape - Group","hd":false},{"ty":"fl","c":{"a":0,"k":[0.328999986836,0.250999989229,0.136999990426,1],"ix":4},"o":{"a":0,"k":100,"ix":5},"r":1,"bm":0,"nm":"Fill 1","mn":"ADBE Vector Graphic - Fill","hd":false},{"ty":"tr","p":{"a":0,"k":[369.783,313.015],"ix":2},"a":{"a":0,"k":[0,0],"ix":1},"s":{"a":0,"k":[100,100],"ix":3},"r":{"a":0,"k":0,"ix":6},"o":{"a":0,"k":100,"ix":7},"sk":{"a":0,"k":0,"ix":4},"sa":{"a":0,"k":0,"ix":5},"nm":"Transform"}],"nm":"Group 4","np":4,"cix":2,"bm":0,"ix":4,"mn":"ADBE Vector Group","hd":false},{"ty":"gr","it":[{"ind":0,"ty":"sh","ix":1,"ks":{"a":0,"k":{"i":[[0,0],[0.629,-1.552],[-1.17,0.496],[-0.083,0.565]],"o":[[0.218,-1.654],[-0.538,1.331],[0.479,-0.313],[0,0]],"v":[[-4.478,16.218],[-7.309,15.395],[-5.361,17.602],[-4.478,16.22]],"c":true},"ix":2},"nm":"Path 1","mn":"ADBE Vector Shape - Group","hd":false},{"ind":1,"ty":"sh","ix":2,"ks":{"a":0,"k":{"i":[[0.005,1.744],[1.249,-1.172],[-0.536,-0.584]],"o":[[-0.115,-1.789],[-0.565,0.556],[1.251,1.215]],"v":[[-2.905,26.211],[-5.267,25.19],[-5.319,27.236]],"c":true},"ix":2},"nm":"Path 2","mn":"ADBE Vector Shape - Group","hd":false},{"ind":2,"ty":"sh","ix":3,"ks":{"a":0,"k":{"i":[[4.643,0.328],[3.283,7.523],[-1.168,0.496],[4.358,20.023],[-2.151,4.681],[0,0],[0,0],[0,0],[0,0],[-5.508,-24.682],[1.469,-0.439],[-2.256,0.314],[-1.081,-2.114],[-0.365,-0.858],[-3.283,-1.457],[0.235,-0.099]],"o":[[-14.349,-0.897],[-1.156,-2.725],[3.426,-1.453],[-5.201,-23.526],[0,0],[0,0],[0,0],[0,0],[-1.235,4.016],[4.338,19.757],[-2.201,0.659],[1.379,-0.217],[0.738,1.524],[1.212,2.425],[1.664,0.673],[-0.233,0.099]],"v":[[11.629,37.507],[-14.065,25.249],[-14.082,21.306],[-15.224,-3.482],[-18.599,-34.401],[-16.898,-37.973],[-10.889,-37.674],[-4.957,-37.341],[-5.824,-34.4],[-1.349,-4.134],[1.858,17.941],[2.227,20.542],[5.406,23.053],[7.413,27.349],[17.987,36.464],[20.514,37.873]],"c":true},"ix":2},"nm":"Path 3","mn":"ADBE Vector Shape - Group","hd":false},{"ty":"mm","mm":1,"nm":"Merge Paths 1","mn":"ADBE Vector Filter - Merge","hd":false},{"ty":"fl","c":{"a":0,"k":[0.944999964097,0.352999997606,0.141000007181,1],"ix":4},"o":{"a":0,"k":100,"ix":5},"r":1,"bm":0,"nm":"Fill 1","mn":"ADBE Vector Graphic - Fill","hd":false},{"ty":"tr","p":{"a":0,"k":[325.69,302.862],"ix":2},"a":{"a":0,"k":[0,0],"ix":1},"s":{"a":0,"k":[100,100],"ix":3},"r":{"a":0,"k":0,"ix":6},"o":{"a":0,"k":100,"ix":7},"sk":{"a":0,"k":0,"ix":4},"sa":{"a":0,"k":0,"ix":5},"nm":"Transform"}],"nm":"Group 5","np":7,"cix":2,"bm":0,"ix":5,"mn":"ADBE Vector Group","hd":false},{"ty":"gr","it":[{"ind":0,"ty":"sh","ix":1,"ks":{"a":0,"k":{"i":[[14.499,-3.302],[-0.393,0.81],[-12.692,1.709]],"o":[[-13.354,3.184],[0.538,-1.331],[8.869,-1.188]],"v":[[5.389,-0.403],[-24.78,4.951],[16.303,-4.574]],"c":true},"ix":2},"nm":"Path 1","mn":"ADBE Vector Shape - Group","hd":false},{"ty":"fl","c":{"a":0,"k":[0.995999983245,0.745000023935,0.282000014361,1],"ix":4},"o":{"a":0,"k":100,"ix":5},"r":1,"bm":0,"nm":"Fill 1","mn":"ADBE Vector Graphic - Fill","hd":false},{"ty":"tr","p":{"a":0,"k":[351.518,225.765],"ix":2},"a":{"a":0,"k":[0,0],"ix":1},"s":{"a":0,"k":[100,100],"ix":3},"r":{"a":0,"k":0,"ix":6},"o":{"a":0,"k":100,"ix":7},"sk":{"a":0,"k":0,"ix":4},"sa":{"a":0,"k":0,"ix":5},"nm":"Transform"}],"nm":"Group 6","np":4,"cix":2,"bm":0,"ix":6,"mn":"ADBE Vector Group","hd":false},{"ty":"gr","it":[{"ind":0,"ty":"sh","ix":1,"ks":{"a":0,"k":{"i":[[4.437,-1.239],[7.363,0.46],[0,0],[0,0],[-0.012,0.189],[-3.857,0.441],[-9.19,3.899],[-1.98,-8.35],[1.982,-1.392]],"o":[[-15.214,4.43],[0,0],[0,0],[-0.698,-3.38],[0.09,-0.222],[13.803,-1.26],[5.53,-2.346],[1.138,4.848],[-2.217,1.492]],"v":[[17.657,6.177],[-25.573,13.672],[-30.106,13.388],[-31.349,7.207],[-32.458,0.693],[-25.378,-0.381],[24.188,-11.574],[31.332,-5.782],[30.386,0.869]],"c":true},"ix":2},"nm":"Path 1","mn":"ADBE Vector Shape - Group","hd":false},{"ty":"fl","c":{"a":0,"k":[0.995999983245,0.745000023935,0.282000014361,1],"ix":4},"o":{"a":0,"k":100,"ix":5},"r":1,"bm":0,"nm":"Fill 1","mn":"ADBE Vector Graphic - Fill","hd":false},{"ty":"tr","p":{"a":0,"k":[352.444,235.554],"ix":2},"a":{"a":0,"k":[0,0],"ix":1},"s":{"a":0,"k":[100,100],"ix":3},"r":{"a":0,"k":0,"ix":6},"o":{"a":0,"k":100,"ix":7},"sk":{"a":0,"k":0,"ix":4},"sa":{"a":0,"k":0,"ix":5},"nm":"Transform"}],"nm":"Group 7","np":4,"cix":2,"bm":0,"ix":7,"mn":"ADBE Vector Group","hd":false},{"ty":"gr","it":[{"ind":0,"ty":"sh","ix":1,"ks":{"a":0,"k":{"i":[[12.847,-4.163],[12.015,-1.788],[-1.063,2.473],[-3.583,1.52],[-5.754,-0.132],[-16.177,6.494],[-5.821,-0.288],[3.557,-0.498],[-0.399,-0.29]],"o":[[-10.178,3.306],[-17.563,2.579],[0.18,-0.444],[5.496,-2.424],[13.974,0.229],[9.568,-3.876],[6.054,0.189],[-0.957,0.129],[1.595,1.161]],"v":[[25.295,-0.719],[-16.744,8.935],[-46.707,9.147],[-39.961,5.55],[-26.942,2.876],[22.798,-7.471],[39.264,-11.332],[44.214,-9.847],[43.145,-9.118]],"c":true},"ix":2},"nm":"Path 1","mn":"ADBE Vector Shape - Group","hd":false},{"ty":"fl","c":{"a":0,"k":[0.995999983245,0.745000023935,0.282000014361,1],"ix":4},"o":{"a":0,"k":100,"ix":5},"r":1,"bm":0,"nm":"Fill 1","mn":"ADBE Vector Graphic - Fill","hd":false},{"ty":"tr","p":{"a":0,"k":[356.076,250.167],"ix":2},"a":{"a":0,"k":[0,0],"ix":1},"s":{"a":0,"k":[100,100],"ix":3},"r":{"a":0,"k":0,"ix":6},"o":{"a":0,"k":100,"ix":7},"sk":{"a":0,"k":0,"ix":4},"sa":{"a":0,"k":0,"ix":5},"nm":"Transform"}],"nm":"Group 8","np":4,"cix":2,"bm":0,"ix":8,"mn":"ADBE Vector Group","hd":false},{"ty":"gr","it":[{"ind":0,"ty":"sh","ix":1,"ks":{"a":0,"k":{"i":[[1.494,1.574],[-0.246,0.795],[-0.727,-1.714]],"o":[[-0.602,-0.575],[0.718,-1.775],[0.86,2.026]],"v":[[-1.838,1.301],[-2.418,-0.934],[1.804,-1.161]],"c":true},"ix":2},"nm":"Path 1","mn":"ADBE Vector Shape - Group","hd":false},{"ty":"fl","c":{"a":0,"k":[0.995999983245,0.745000023935,0.282000014361,1],"ix":4},"o":{"a":0,"k":100,"ix":5},"r":1,"bm":0,"nm":"Fill 1","mn":"ADBE Vector Graphic - Fill","hd":false},{"ty":"tr","p":{"a":0,"k":[341.55,283.829],"ix":2},"a":{"a":0,"k":[0,0],"ix":1},"s":{"a":0,"k":[100,100],"ix":3},"r":{"a":0,"k":0,"ix":6},"o":{"a":0,"k":100,"ix":7},"sk":{"a":0,"k":0,"ix":4},"sa":{"a":0,"k":0,"ix":5},"nm":"Transform"}],"nm":"Group 9","np":4,"cix":2,"bm":0,"ix":9,"mn":"ADBE Vector Group","hd":false},{"ty":"gr","it":[{"ind":0,"ty":"sh","ix":1,"ks":{"a":0,"k":{"i":[[1.525,1.648],[-1.611,0.316],[-0.528,-1.246]],"o":[[-1.494,-1.572],[1.001,-0.241],[0.958,2.259]],"v":[[-1.064,1.39],[-0.727,-2.797],[1.6,-1.211]],"c":true},"ix":2},"nm":"Path 1","mn":"ADBE Vector Shape - Group","hd":false},{"ty":"fl","c":{"a":0,"k":[0.995999983245,0.745000023935,0.282000014361,1],"ix":4},"o":{"a":0,"k":100,"ix":5},"r":1,"bm":0,"nm":"Fill 1","mn":"ADBE Vector Graphic - Fill","hd":false},{"ty":"tr","p":{"a":0,"k":[384.945,275.207],"ix":2},"a":{"a":0,"k":[0,0],"ix":1},"s":{"a":0,"k":[100,100],"ix":3},"r":{"a":0,"k":0,"ix":6},"o":{"a":0,"k":100,"ix":7},"sk":{"a":0,"k":0,"ix":4},"sa":{"a":0,"k":0,"ix":5},"nm":"Transform"}],"nm":"Group 10","np":4,"cix":2,"bm":0,"ix":10,"mn":"ADBE Vector Group","hd":false},{"ty":"gr","it":[{"ind":0,"ty":"sh","ix":1,"ks":{"a":0,"k":{"i":[[8.104,-1.691],[0.543,0.413],[-0.46,1.299],[-4.502,0.438],[-2.957,1.255],[-0.691,-2.281],[2.814,-1.379]],"o":[[-8.072,1.771],[-1.02,-0.67],[0.102,-0.41],[8.39,-0.801],[1.403,-0.595],[0.758,2.435],[-1.68,0.803]],"v":[[-1.359,4.146],[-17.055,6.578],[-18.92,0.016],[-10.48,-1.54],[16.129,-6.396],[18.621,-4.419],[16.397,-0.352]],"c":true},"ix":2},"nm":"Path 1","mn":"ADBE Vector Shape - Group","hd":false},{"ty":"fl","c":{"a":0,"k":[0.995999983245,0.745000023935,0.282000014361,1],"ix":4},"o":{"a":0,"k":100,"ix":5},"r":1,"bm":0,"nm":"Fill 1","mn":"ADBE Vector Graphic - Fill","hd":false},{"ty":"tr","p":{"a":0,"k":[369.126,313.106],"ix":2},"a":{"a":0,"k":[0,0],"ix":1},"s":{"a":0,"k":[100,100],"ix":3},"r":{"a":0,"k":0,"ix":6},"o":{"a":0,"k":100,"ix":7},"sk":{"a":0,"k":0,"ix":4},"sa":{"a":0,"k":0,"ix":5},"nm":"Transform"}],"nm":"Group 11","np":4,"cix":2,"bm":0,"ix":11,"mn":"ADBE Vector Group","hd":false},{"ty":"gr","it":[{"ind":0,"ty":"sh","ix":1,"ks":{"a":0,"k":{"i":[[-2.754,2.825],[1.552,3.661],[-1.961,1.66],[0,0],[0,0],[3.61,0.491],[-0.397,-0.936],[-1.579,-0.565],[0,0],[0,0],[-5.364,-0.298]],"o":[[2.476,-2.613],[-0.991,-2.337],[0,0],[0,0],[-2.179,0.28],[-5.374,-0.752],[1.493,0.763],[0,0],[0,0],[-1.795,5.082],[3.999,0.328]],"v":[[-13.297,-2.501],[-11.953,-11.25],[-10.837,-15.768],[-8.677,-17.603],[-12.578,-17.051],[-23.052,-17.479],[-35.552,-17.047],[-30.938,-15.052],[-26.389,-13.214],[-27.254,-10.918],[-20.051,-0.004]],"c":true},"ix":2},"nm":"Path 1","mn":"ADBE Vector Shape - Group","hd":false},{"ind":1,"ty":"sh","ix":2,"ks":{"a":0,"k":{"i":[[-0.908,2.41],[3.236,2.212],[-1.714,0.726],[-0.734,0.886],[6.51,-2.853],[-1.401,-0.049],[0.302,-3.62],[-1.769,-2.005],[-3.971,1.685]],"o":[[1.401,-3.627],[-2.039,-1.34],[1.047,-0.475],[0.547,-0.875],[-7.165,3.04],[2,0.163],[-0.123,3.177],[2.656,3.009],[2.492,-1.056]],"v":[[31.896,-14.686],[28.556,-24.94],[28.276,-27.118],[30.983,-29.186],[22.118,-26.253],[14.349,-22.038],[16.047,-18.255],[17.978,-12.184],[27.525,-10.259]],"c":true},"ix":2},"nm":"Path 2","mn":"ADBE Vector Shape - Group","hd":false},{"ind":2,"ty":"sh","ix":3,"ks":{"a":0,"k":{"i":[[0,0],[0.629,-1.552],[-1.169,0.496],[-0.082,0.566]],"o":[[0.217,-1.654],[-0.538,1.331],[0.478,-0.314],[0,0]],"v":[[-39.104,25.267],[-41.935,24.444],[-39.987,26.65],[-39.107,25.267]],"c":true},"ix":2},"nm":"Path 3","mn":"ADBE Vector Shape - Group","hd":false},{"ind":3,"ty":"sh","ix":4,"ks":{"a":0,"k":{"i":[[0,0],[1.293,-1.284],[-1.48,0.628],[0.03,0.723]],"o":[[-0.016,-1.555],[-1.126,1.028],[0.544,-0.231],[0,0]],"v":[[-26.797,22.435],[-29.671,21.725],[-27.703,24.198],[-26.797,22.435]],"c":true},"ix":2},"nm":"Path 4","mn":"ADBE Vector Shape - Group","hd":false},{"ind":4,"ty":"sh","ix":5,"ks":{"a":0,"k":{"i":[[0,0],[0.856,-0.364],[-1.475,-0.661],[0.496,1.168]],"o":[[-0.264,-0.623],[-1.48,0.627],[1.075,0.371],[0,0]],"v":[[-19.723,20.262],[-21.742,19.832],[-21.742,22.866],[-19.724,20.262]],"c":true},"ix":2},"nm":"Path 5","mn":"ADBE Vector Shape - Group","hd":false},{"ind":5,"ty":"sh","ix":6,"ks":{"a":0,"k":{"i":[[0,0],[0.628,-1.55],[-1.169,0.495],[-0.083,0.565]],"o":[[0.217,-1.655],[-0.538,1.332],[0.479,-0.315],[0,0]],"v":[[-31.34,28.406],[-34.169,27.582],[-32.223,29.79],[-31.34,28.408]],"c":true},"ix":2},"nm":"Path 6","mn":"ADBE Vector Shape - Group","hd":false},{"ind":6,"ty":"sh","ix":7,"ks":{"a":0,"k":{"i":[[0.003,1.745],[1.249,-1.171],[-0.537,-0.585]],"o":[[-0.117,-1.789],[-0.565,0.556],[1.25,1.215]],"v":[[-37.53,35.259],[-39.893,34.238],[-39.944,36.284]],"c":true},"ix":2},"nm":"Path 7","mn":"ADBE Vector Shape - Group","hd":false},{"ind":7,"ty":"sh","ix":8,"ks":{"a":0,"k":{"i":[[0,0],[0.483,-1.032],[-1.479,0.628],[0.263,0.623]],"o":[[-0.495,-1.169],[-0.549,1.519],[0.855,-0.362],[0,0]],"v":[[-17.578,29.646],[-20.855,29.289],[-18.674,31.396],[-17.581,29.646]],"c":true},"ix":2},"nm":"Path 8","mn":"ADBE Vector Shape - Group","hd":false},{"ind":8,"ty":"sh","ix":9,"ks":{"a":0,"k":{"i":[[0,0],[-0.496,-1.169],[-0.411,-0.101],[0.909,0.626]],"o":[[-1.086,-0.826],[0.265,0.623],[0.995,0.405],[0,0]],"v":[[38.461,7.068],[35.945,8.501],[37.151,9.828],[38.458,7.068]],"c":true},"ix":2},"nm":"Path 9","mn":"ADBE Vector Shape - Group","hd":false},{"ind":9,"ty":"sh","ix":10,"ks":{"a":0,"k":{"i":[[0,0],[-0.382,-1.768],[-0.991,0.696],[0.264,0.624]],"o":[[-0.729,-1.715],[0.229,1.19],[0.71,-0.485],[0,0]],"v":[[45.465,6.026],[42.992,7.35],[44.656,8.023],[45.461,6.027]],"c":true},"ix":2},"nm":"Path 10","mn":"ADBE Vector Shape - Group","hd":false},{"ind":10,"ty":"sh","ix":11,"ks":{"a":0,"k":{"i":[[0.528,1.246],[0.582,-1.442],[-0.481,-0.452]],"o":[[-0.66,-1.557],[-0.251,0.611],[1.305,0.916]],"v":[[-23.717,36.844],[-26.803,36.499],[-26.421,38.266]],"c":true},"ix":2},"nm":"Path 11","mn":"ADBE Vector Shape - Group","hd":false},{"ind":11,"ty":"sh","ix":12,"ks":{"a":0,"k":{"i":[[0,0],[0.701,-0.298],[-1.119,-0.904],[0.348,1.689]],"o":[[-0.175,-0.845],[-1.403,0.595],[1.166,0.791],[0,0]],"v":[[51.802,9.496],[50.306,8.568],[49.694,11.676],[51.803,9.495]],"c":true},"ix":2},"nm":"Path 12","mn":"ADBE Vector Shape - Group","hd":false},{"ind":12,"ty":"sh","ix":13,"ks":{"a":0,"k":{"i":[[0,0],[0.614,-0.285],[-1.331,-0.538],[0.562,1.325]],"o":[[-0.288,-0.613],[-1.168,0.496],[1.078,0.372],[0,0]],"v":[[40.388,16.818],[38.758,16.224],[39.147,19.091],[40.389,16.818]],"c":true},"ix":2},"nm":"Path 13","mn":"ADBE Vector Shape - Group","hd":false},{"ind":13,"ty":"sh","ix":14,"ks":{"a":0,"k":{"i":[[-1.105,1.939],[1.223,2.882],[11.596,-2.346],[5.034,-0.481],[0.619,-2.007],[-1.071,-4.693],[0,0],[0,0],[0,0],[0,0],[-2.113,0.436]],"o":[[0.772,-1.43],[-1.388,-3.271],[-5.992,1.256],[-10.134,0.807],[-0.236,0.744],[0,0],[0,0],[0,0],[0,0],[7.821,-3.227],[3.993,-0.774]],"v":[[33.608,20.982],[32.577,11.401],[16.949,10.31],[-3.181,13.336],[-15.591,16.577],[-14.049,26.492],[-12.004,34.999],[-8.975,36.286],[-5.982,37.497],[8.337,31.607],[26.382,24.965]],"c":true},"ix":2},"nm":"Path 14","mn":"ADBE Vector Shape - Group","hd":false},{"ind":14,"ty":"sh","ix":15,"ks":{"a":0,"k":{"i":[[0.361,1.502],[0.767,-0.143],[-0.331,-0.778]],"o":[[-0.087,-0.422],[-0.924,0.208],[0.562,1.326]],"v":[[48.75,20.714],[47.152,20.198],[46.181,21.803]],"c":true},"ix":2},"nm":"Path 15","mn":"ADBE Vector Shape - Group","hd":false},{"ind":15,"ty":"sh","ix":16,"ks":{"a":0,"k":{"i":[[6.64,-1.896],[9.82,9.068],[5.515,25.782],[-3.608,5.575],[0,0],[0,0],[-19.443,3.561],[-15.308,5.942],[-1.572,-1.539],[1.247,-0.529],[-2.714,-14.196],[-1.977,0.103],[-0.366,-0.771],[1.501,-0.36],[-0.412,-3.135],[-2.259,0.958],[-0.371,-1.956],[1.723,-0.271],[-0.528,-1.246],[-0.623,0.265],[1.058,-3.574],[4.243,-2.994]],"o":[[-34.007,9.739],[-4.196,-3.826],[-5.559,-25.672],[0,0],[0,0],[6.257,2.4],[17.754,-3.212],[14.029,-5.492],[2.491,2.62],[-1.715,0.727],[2.755,14.73],[0.851,0.08],[0.43,1.012],[-1.88,0.338],[0.618,4.057],[1.246,-0.529],[0.871,4.869],[-1.3,0.184],[0.364,0.857],[1.481,-0.627],[-0.663,2.119],[-4.988,3.404]],"v":[[29.108,38.971],[-44.504,40.055],[-55.72,6.031],[-57.773,-27.837],[-55.797,-30.973],[-52.978,-29.962],[-13.29,-31.727],[29.724,-43.632],[45.358,-47.507],[48.702,-38.54],[49.721,-22.707],[55.146,-5.799],[57.107,-4.427],[55.668,-2.621],[54.053,1.372],[57.704,5.43],[59.642,7.18],[58.811,12.587],[57.781,14.495],[59.565,15.667],[60.324,21.137],[54,27.677]],"c":true},"ix":2},"nm":"Path 16","mn":"ADBE Vector Shape - Group","hd":false},{"ty":"mm","mm":1,"nm":"Merge Paths 1","mn":"ADBE Vector Filter - Merge","hd":false},{"ty":"fl","c":{"a":0,"k":[0.995999983245,0.745000023935,0.282000014361,1],"ix":4},"o":{"a":0,"k":100,"ix":5},"r":1,"bm":0,"nm":"Fill 1","mn":"ADBE Vector Graphic - Fill","hd":false},{"ty":"tr","p":{"a":0,"k":[360.318,293.813],"ix":2},"a":{"a":0,"k":[0,0],"ix":1},"s":{"a":0,"k":[100,100],"ix":3},"r":{"a":0,"k":0,"ix":6},"o":{"a":0,"k":100,"ix":7},"sk":{"a":0,"k":0,"ix":4},"sa":{"a":0,"k":0,"ix":5},"nm":"Transform"}],"nm":"Group 12","np":20,"cix":2,"bm":0,"ix":12,"mn":"ADBE Vector Group","hd":false},{"ty":"gr","it":[{"ind":0,"ty":"sh","ix":1,"ks":{"a":0,"k":{"i":[[3.794,-0.962],[0.318,4],[0.074,0.609],[-4.687,-0.219],[-14.41,3.724],[-0.823,-0.203],[-0.429,-1.01],[4.238,-1.707]],"o":[[-18.524,4.642],[-0.097,-0.878],[-0.142,-0.767],[8.509,0.341],[6.127,-1.587],[0.821,0.203],[0.76,1.791],[-3.675,1.348]],"v":[[11.345,2.246],[-26.596,3.361],[-26.853,0.805],[-20.207,0.009],[11.437,-4.684],[23.989,-7.159],[26.235,-4.896],[22.556,-1.221]],"c":true},"ix":2},"nm":"Path 1","mn":"ADBE Vector Shape - Group","hd":false},{"ty":"fl","c":{"a":0,"k":[0.995999983245,0.745000023935,0.282000014361,1],"ix":4},"o":{"a":0,"k":100,"ix":5},"r":1,"bm":0,"nm":"Fill 1","mn":"ADBE Vector Graphic - Fill","hd":false},{"ty":"tr","p":{"a":0,"k":[371.09,346.554],"ix":2},"a":{"a":0,"k":[0,0],"ix":1},"s":{"a":0,"k":[100,100],"ix":3},"r":{"a":0,"k":0,"ix":6},"o":{"a":0,"k":100,"ix":7},"sk":{"a":0,"k":0,"ix":4},"sa":{"a":0,"k":0,"ix":5},"nm":"Transform"}],"nm":"Group 13","np":4,"cix":2,"bm":0,"ix":13,"mn":"ADBE Vector Group","hd":false},{"ty":"gr","it":[{"ind":0,"ty":"sh","ix":1,"ks":{"a":0,"k":{"i":[[14.499,-3.302],[-0.393,0.81],[-12.692,1.709]],"o":[[-13.354,3.184],[0.538,-1.331],[8.869,-1.188]],"v":[[5.389,-0.403],[-24.78,4.951],[16.303,-4.574]],"c":true},"ix":2},"nm":"Path 1","mn":"ADBE Vector Shape - Group","hd":false},{"ty":"fl","c":{"a":0,"k":[0.987999949736,0.451000019148,0.125,1],"ix":4},"o":{"a":0,"k":100,"ix":5},"r":1,"bm":0,"nm":"Fill 1","mn":"ADBE Vector Graphic - Fill","hd":false},{"ty":"tr","p":{"a":0,"k":[351.518,225.765],"ix":2},"a":{"a":0,"k":[0,0],"ix":1},"s":{"a":0,"k":[100,100],"ix":3},"r":{"a":0,"k":0,"ix":6},"o":{"a":0,"k":100,"ix":7},"sk":{"a":0,"k":0,"ix":4},"sa":{"a":0,"k":0,"ix":5},"nm":"Transform"}],"nm":"Group 14","np":4,"cix":2,"bm":0,"ix":14,"mn":"ADBE Vector Group","hd":false},{"ty":"gr","it":[{"ind":0,"ty":"sh","ix":1,"ks":{"a":0,"k":{"i":[[4.437,-1.239],[7.363,0.46],[0,0],[0,0],[-0.012,0.189],[-3.857,0.441],[-9.19,3.899],[-1.98,-8.35],[1.982,-1.392]],"o":[[-15.214,4.43],[0,0],[0,0],[-0.698,-3.38],[0.09,-0.222],[13.803,-1.26],[5.53,-2.346],[1.138,4.848],[-2.217,1.492]],"v":[[17.657,6.177],[-25.573,13.672],[-30.106,13.388],[-31.349,7.207],[-32.458,0.693],[-25.378,-0.381],[24.188,-11.574],[31.332,-5.782],[30.386,0.869]],"c":true},"ix":2},"nm":"Path 1","mn":"ADBE Vector Shape - Group","hd":false},{"ty":"fl","c":{"a":0,"k":[0.987999949736,0.451000019148,0.125,1],"ix":4},"o":{"a":0,"k":100,"ix":5},"r":1,"bm":0,"nm":"Fill 1","mn":"ADBE Vector Graphic - Fill","hd":false},{"ty":"tr","p":{"a":0,"k":[352.444,235.554],"ix":2},"a":{"a":0,"k":[0,0],"ix":1},"s":{"a":0,"k":[100,100],"ix":3},"r":{"a":0,"k":0,"ix":6},"o":{"a":0,"k":100,"ix":7},"sk":{"a":0,"k":0,"ix":4},"sa":{"a":0,"k":0,"ix":5},"nm":"Transform"}],"nm":"Group 15","np":4,"cix":2,"bm":0,"ix":15,"mn":"ADBE Vector Group","hd":false},{"ty":"gr","it":[{"ind":0,"ty":"sh","ix":1,"ks":{"a":0,"k":{"i":[[8.666,-2.757],[11.751,-1.768],[-1.065,2.473],[-3.583,1.52],[-5.754,-0.132],[-16.177,6.495],[-6.087,-0.266],[0.271,-0.666]],"o":[[-10.555,3.283],[-17.562,2.579],[0.18,-0.444],[5.496,-2.423],[13.975,0.23],[9.645,-3.908],[4.198,0.149],[-0.671,1.665]],"v":[[26.376,-0.658],[-15.696,8.919],[-45.658,9.131],[-38.912,5.533],[-25.894,2.86],[23.847,-7.489],[40.502,-11.338],[46.451,-10.093]],"c":true},"ix":2},"nm":"Path 1","mn":"ADBE Vector Shape - Group","hd":false},{"ty":"fl","c":{"a":0,"k":[0.987999949736,0.451000019148,0.125,1],"ix":4},"o":{"a":0,"k":100,"ix":5},"r":1,"bm":0,"nm":"Fill 1","mn":"ADBE Vector Graphic - Fill","hd":false},{"ty":"tr","p":{"a":0,"k":[355.026,250.183],"ix":2},"a":{"a":0,"k":[0,0],"ix":1},"s":{"a":0,"k":[100,100],"ix":3},"r":{"a":0,"k":0,"ix":6},"o":{"a":0,"k":100,"ix":7},"sk":{"a":0,"k":0,"ix":4},"sa":{"a":0,"k":0,"ix":5},"nm":"Transform"}],"nm":"Group 16","np":4,"cix":2,"bm":0,"ix":16,"mn":"ADBE Vector Group","hd":false},{"ty":"gr","it":[{"ind":0,"ty":"sh","ix":1,"ks":{"a":0,"k":{"i":[[1.494,1.574],[-0.246,0.795],[-0.727,-1.714]],"o":[[-0.602,-0.575],[0.718,-1.775],[0.86,2.026]],"v":[[-1.838,1.301],[-2.418,-0.934],[1.804,-1.161]],"c":true},"ix":2},"nm":"Path 1","mn":"ADBE Vector Shape - Group","hd":false},{"ty":"fl","c":{"a":0,"k":[0.987999949736,0.451000019148,0.125,1],"ix":4},"o":{"a":0,"k":100,"ix":5},"r":1,"bm":0,"nm":"Fill 1","mn":"ADBE Vector Graphic - Fill","hd":false},{"ty":"tr","p":{"a":0,"k":[341.55,283.829],"ix":2},"a":{"a":0,"k":[0,0],"ix":1},"s":{"a":0,"k":[100,100],"ix":3},"r":{"a":0,"k":0,"ix":6},"o":{"a":0,"k":100,"ix":7},"sk":{"a":0,"k":0,"ix":4},"sa":{"a":0,"k":0,"ix":5},"nm":"Transform"}],"nm":"Group 17","np":4,"cix":2,"bm":0,"ix":17,"mn":"ADBE Vector Group","hd":false},{"ty":"gr","it":[{"ind":0,"ty":"sh","ix":1,"ks":{"a":0,"k":{"i":[[1.525,1.648],[-1.611,0.316],[-0.528,-1.246]],"o":[[-1.494,-1.572],[1.001,-0.241],[0.958,2.259]],"v":[[-1.064,1.39],[-0.727,-2.797],[1.6,-1.211]],"c":true},"ix":2},"nm":"Path 1","mn":"ADBE Vector Shape - Group","hd":false},{"ty":"fl","c":{"a":0,"k":[0.987999949736,0.451000019148,0.125,1],"ix":4},"o":{"a":0,"k":100,"ix":5},"r":1,"bm":0,"nm":"Fill 1","mn":"ADBE Vector Graphic - Fill","hd":false},{"ty":"tr","p":{"a":0,"k":[384.945,275.207],"ix":2},"a":{"a":0,"k":[0,0],"ix":1},"s":{"a":0,"k":[100,100],"ix":3},"r":{"a":0,"k":0,"ix":6},"o":{"a":0,"k":100,"ix":7},"sk":{"a":0,"k":0,"ix":4},"sa":{"a":0,"k":0,"ix":5},"nm":"Transform"}],"nm":"Group 18","np":4,"cix":2,"bm":0,"ix":18,"mn":"ADBE Vector Group","hd":false},{"ty":"gr","it":[{"ind":0,"ty":"sh","ix":1,"ks":{"a":0,"k":{"i":[[8.104,-1.691],[0.543,0.413],[-0.46,1.299],[-4.502,0.438],[-2.957,1.255],[-0.691,-2.281],[2.814,-1.379]],"o":[[-8.072,1.771],[-1.02,-0.67],[0.102,-0.41],[8.39,-0.801],[1.403,-0.595],[0.758,2.435],[-1.68,0.803]],"v":[[-1.359,4.146],[-17.055,6.578],[-18.92,0.016],[-10.48,-1.54],[16.129,-6.396],[18.621,-4.419],[16.397,-0.352]],"c":true},"ix":2},"nm":"Path 1","mn":"ADBE Vector Shape - Group","hd":false},{"ty":"fl","c":{"a":0,"k":[0.987999949736,0.451000019148,0.125,1],"ix":4},"o":{"a":0,"k":100,"ix":5},"r":1,"bm":0,"nm":"Fill 1","mn":"ADBE Vector Graphic - Fill","hd":false},{"ty":"tr","p":{"a":0,"k":[369.126,313.106],"ix":2},"a":{"a":0,"k":[0,0],"ix":1},"s":{"a":0,"k":[100,100],"ix":3},"r":{"a":0,"k":0,"ix":6},"o":{"a":0,"k":100,"ix":7},"sk":{"a":0,"k":0,"ix":4},"sa":{"a":0,"k":0,"ix":5},"nm":"Transform"}],"nm":"Group 19","np":4,"cix":2,"bm":0,"ix":19,"mn":"ADBE Vector Group","hd":false},{"ty":"gr","it":[{"ind":0,"ty":"sh","ix":1,"ks":{"a":0,"k":{"i":[[-2.754,2.825],[1.552,3.661],[-1.961,1.66],[0,0],[0,0],[3.61,0.491],[-0.397,-0.936],[-1.579,-0.565],[0,0],[0,0],[-5.364,-0.298]],"o":[[2.476,-2.613],[-0.991,-2.337],[0,0],[0,0],[-2.179,0.28],[-5.374,-0.752],[1.493,0.763],[0,0],[0,0],[-1.795,5.081],[3.999,0.328]],"v":[[-16.668,-0.468],[-15.324,-9.217],[-14.208,-13.735],[-12.048,-15.57],[-15.948,-15.018],[-26.423,-15.446],[-38.922,-15.014],[-34.308,-13.02],[-29.76,-11.181],[-30.624,-8.885],[-23.421,2.029]],"c":true},"ix":2},"nm":"Path 1","mn":"ADBE Vector Shape - Group","hd":false},{"ind":1,"ty":"sh","ix":2,"ks":{"a":0,"k":{"i":[[-0.908,2.41],[3.236,2.212],[-1.714,0.726],[-0.734,0.886],[6.51,-2.853],[-1.401,-0.049],[0.302,-3.62],[-1.769,-2.005],[-3.971,1.685]],"o":[[1.401,-3.627],[-2.039,-1.34],[1.047,-0.475],[0.547,-0.875],[-7.165,3.04],[2,0.163],[-0.123,3.177],[2.656,3.009],[2.492,-1.056]],"v":[[28.525,-12.653],[25.186,-22.908],[24.906,-25.086],[27.613,-27.154],[18.748,-24.22],[10.978,-20.005],[12.676,-16.222],[14.607,-10.151],[24.154,-8.226]],"c":true},"ix":2},"nm":"Path 2","mn":"ADBE Vector Shape - Group","hd":false},{"ind":2,"ty":"sh","ix":3,"ks":{"a":0,"k":{"i":[[0,0],[0.628,-1.551],[-1.169,0.496],[-0.082,0.566]],"o":[[0.217,-1.654],[-0.539,1.331],[0.478,-0.315],[0,0]],"v":[[-42.476,27.3],[-45.306,26.477],[-43.358,28.684],[-42.477,27.3]],"c":true},"ix":2},"nm":"Path 3","mn":"ADBE Vector Shape - Group","hd":false},{"ind":3,"ty":"sh","ix":4,"ks":{"a":0,"k":{"i":[[0,0],[1.293,-1.284],[-1.48,0.628],[0.03,0.723]],"o":[[-0.017,-1.555],[-1.126,1.028],[0.545,-0.232],[0,0]],"v":[[-30.167,24.468],[-33.042,23.758],[-31.074,26.232],[-30.168,24.468]],"c":true},"ix":2},"nm":"Path 4","mn":"ADBE Vector Shape - Group","hd":false},{"ind":4,"ty":"sh","ix":5,"ks":{"a":0,"k":{"i":[[0,0],[0.856,-0.364],[-1.475,-0.661],[0.496,1.168]],"o":[[-0.264,-0.624],[-1.48,0.627],[1.076,0.371],[0,0]],"v":[[-23.094,22.295],[-25.114,21.865],[-25.114,24.898],[-23.095,22.295]],"c":true},"ix":2},"nm":"Path 5","mn":"ADBE Vector Shape - Group","hd":false},{"ind":5,"ty":"sh","ix":6,"ks":{"a":0,"k":{"i":[[0,0],[0.628,-1.55],[-1.17,0.496],[-0.083,0.565]],"o":[[0.217,-1.655],[-0.538,1.333],[0.478,-0.314],[0,0]],"v":[[-34.711,30.439],[-37.541,29.615],[-35.593,31.823],[-34.711,30.44]],"c":true},"ix":2},"nm":"Path 6","mn":"ADBE Vector Shape - Group","hd":false},{"ind":6,"ty":"sh","ix":7,"ks":{"a":0,"k":{"i":[[0,0],[0.942,0.704],[0.273,-1.311],[-0.925,-2.181],[-0.643,2.385]],"o":[[0.417,-1.831],[-1.02,-0.67],[-0.205,1.466],[1.155,2.727],[0,0]],"v":[[53.228,-5.118],[47.111,-36.436],[43.983,-34.926],[49.553,-5.766],[53.227,-5.118]],"c":true},"ix":2},"nm":"Path 7","mn":"ADBE Vector Shape - Group","hd":false},{"ind":7,"ty":"sh","ix":8,"ks":{"a":0,"k":{"i":[[0.003,1.745],[1.249,-1.171],[-0.537,-0.585]],"o":[[-0.117,-1.789],[-0.565,0.556],[1.25,1.215]],"v":[[-40.9,37.292],[-43.264,36.271],[-43.315,38.317]],"c":true},"ix":2},"nm":"Path 8","mn":"ADBE Vector Shape - Group","hd":false},{"ind":8,"ty":"sh","ix":9,"ks":{"a":0,"k":{"i":[[0,0],[0.482,-1.032],[-1.479,0.628],[0.263,0.623]],"o":[[-0.496,-1.169],[-0.549,1.519],[0.853,-0.36],[0,0]],"v":[[-20.947,31.676],[-24.224,31.32],[-22.043,33.427],[-20.951,31.679]],"c":true},"ix":2},"nm":"Path 9","mn":"ADBE Vector Shape - Group","hd":false},{"ind":9,"ty":"sh","ix":10,"ks":{"a":0,"k":{"i":[[0,0],[-0.496,-1.168],[-0.41,-0.102],[0.909,0.626]],"o":[[-1.086,-0.826],[0.264,0.624],[0.994,0.407],[0,0]],"v":[[35.093,9.098],[32.577,10.532],[33.782,11.859],[35.088,9.101]],"c":true},"ix":2},"nm":"Path 10","mn":"ADBE Vector Shape - Group","hd":false},{"ind":10,"ty":"sh","ix":11,"ks":{"a":0,"k":{"i":[[0,0],[-0.383,-1.767],[-0.991,0.696],[0.264,0.624]],"o":[[-0.728,-1.715],[0.229,1.19],[0.709,-0.483],[0,0]],"v":[[42.095,8.057],[39.624,9.382],[41.287,10.054],[42.091,8.06]],"c":true},"ix":2},"nm":"Path 11","mn":"ADBE Vector Shape - Group","hd":false},{"ind":11,"ty":"sh","ix":12,"ks":{"a":0,"k":{"i":[[0,0],[0.582,-1.442],[-0.482,-0.453],[0.528,1.246]],"o":[[-0.661,-1.557],[-0.252,0.611],[1.304,0.918],[0,0]],"v":[[-27.086,38.875],[-30.172,38.53],[-29.79,40.297],[-27.088,38.877]],"c":true},"ix":2},"nm":"Path 12","mn":"ADBE Vector Shape - Group","hd":false},{"ind":12,"ty":"sh","ix":13,"ks":{"a":0,"k":{"i":[[0,0],[2.182,-0.925],[-0.336,-2.522],[0.487,6.134]],"o":[[-0.252,-3.844],[-1.089,0.462],[0.864,6.159],[0,0]],"v":[[54.83,3.206],[51.733,-0.626],[50.719,3.481],[54.829,3.208]],"c":true},"ix":2},"nm":"Path 13","mn":"ADBE Vector Shape - Group","hd":false},{"ind":13,"ty":"sh","ix":14,"ks":{"a":0,"k":{"i":[[0,0],[0.702,-0.298],[-1.118,-0.903],[0.348,1.689]],"o":[[-0.175,-0.845],[-1.401,0.595],[1.165,0.794],[0,0]],"v":[[48.434,11.526],[46.936,10.599],[46.325,13.706],[48.433,11.528]],"c":true},"ix":2},"nm":"Path 14","mn":"ADBE Vector Shape - Group","hd":false},{"ind":14,"ty":"sh","ix":15,"ks":{"a":0,"k":{"i":[[0,0],[0.614,-0.285],[-1.332,-0.539],[0.562,1.325]],"o":[[-0.288,-0.613],[-1.169,0.496],[1.076,0.374],[0,0]],"v":[[37.02,18.849],[35.389,18.254],[35.778,21.122],[37.019,18.851]],"c":true},"ix":2},"nm":"Path 15","mn":"ADBE Vector Shape - Group","hd":false},{"ind":15,"ty":"sh","ix":16,"ks":{"a":0,"k":{"i":[[0,0],[1.223,2.882],[11.596,-2.346],[5.034,-0.481],[0.618,-2.007],[-1.071,-4.692],[0,0],[0,0],[0,0],[0,0],[-2.114,0.437],[-1.105,1.939]],"o":[[0.772,-1.431],[-1.388,-3.271],[-5.992,1.256],[-10.135,0.807],[-0.236,0.744],[0,0],[0,0],[0,0],[0,0],[7.821,-3.226],[3.991,-0.771],[0,0]],"v":[[30.238,23.012],[29.207,13.432],[13.581,12.341],[-6.549,15.366],[-18.959,18.607],[-17.419,28.522],[-15.372,37.029],[-12.345,38.317],[-9.35,39.528],[4.969,33.637],[23.013,26.994],[30.237,23.014]],"c":true},"ix":2},"nm":"Path 16","mn":"ADBE Vector Shape - Group","hd":false},{"ind":16,"ty":"sh","ix":17,"ks":{"a":0,"k":{"i":[[0,0],[0.623,-0.265],[-0.363,-0.857],[-0.623,0.264],[0.364,0.857]],"o":[[-0.364,-0.858],[-0.623,0.265],[0.364,0.857],[0.623,-0.264],[0,0]],"v":[[56.782,15.612],[54.953,14.55],[54.445,16.603],[56.274,17.665],[56.78,15.614]],"c":true},"ix":2},"nm":"Path 17","mn":"ADBE Vector Shape - Group","hd":false},{"ind":17,"ty":"sh","ix":18,"ks":{"a":0,"k":{"i":[[0.361,1.502],[0.767,-0.143],[-0.331,-0.778]],"o":[[-0.087,-0.422],[-0.924,0.208],[0.562,1.326]],"v":[[45.38,22.746],[43.782,22.23],[42.81,23.836]],"c":true},"ix":2},"nm":"Path 18","mn":"ADBE Vector Shape - Group","hd":false},{"ind":18,"ty":"sh","ix":19,"ks":{"a":0,"k":{"i":[[7.563,-2.103],[9.82,9.068],[5.515,25.782],[-3.608,5.575],[0,0],[0,0],[-19.443,3.561],[-14.764,5.711],[-1.595,1.871],[0,0],[0,0],[-2.775,-12.607],[0.163,-2],[9.5,-6.419]],"o":[[-34.007,9.739],[-4.196,-3.826],[-5.559,-25.672],[0,0],[0,0],[6.257,2.4],[17.597,-3.146],[11.302,-4.335],[0,0],[0,0],[5.719,3.731],[5.716,25.606],[-0.479,6.453],[-6.69,4.584]],"v":[[25.738,41.004],[-47.874,42.088],[-59.091,8.064],[-61.144,-25.804],[-59.167,-28.94],[-56.349,-27.929],[-16.661,-29.694],[25.809,-41.368],[41.288,-48.854],[43.251,-51.157],[46.375,-48.99],[55.785,-30.926],[64.589,12.577],[52.177,28.595]],"c":true},"ix":2},"nm":"Path 19","mn":"ADBE Vector Shape - Group","hd":false},{"ty":"mm","mm":1,"nm":"Merge Paths 1","mn":"ADBE Vector Filter - Merge","hd":false},{"ty":"fl","c":{"a":0,"k":[0.987999949736,0.451000019148,0.125,1],"ix":4},"o":{"a":0,"k":100,"ix":5},"r":1,"bm":0,"nm":"Fill 1","mn":"ADBE Vector Graphic - Fill","hd":false},{"ty":"tr","p":{"a":0,"k":[363.688,291.78],"ix":2},"a":{"a":0,"k":[0,0],"ix":1},"s":{"a":0,"k":[100,100],"ix":3},"r":{"a":0,"k":0,"ix":6},"o":{"a":0,"k":100,"ix":7},"sk":{"a":0,"k":0,"ix":4},"sa":{"a":0,"k":0,"ix":5},"nm":"Transform"}],"nm":"Group 20","np":23,"cix":2,"bm":0,"ix":20,"mn":"ADBE Vector Group","hd":false},{"ty":"gr","it":[{"ind":0,"ty":"sh","ix":1,"ks":{"a":0,"k":{"i":[[7.004,-1.685],[5.704,1.532],[0.757,2.437],[-0.09,0.221],[-3.235,0.175],[-14.904,4.943],[-0.867,-3.125],[1.626,-1.15]],"o":[[-13.398,3.294],[-2.277,-0.596],[-0.583,-1.591],[0.045,-0.112],[12.388,-0.476],[7.63,-2.594],[0.538,1.702],[-3.532,2.507]],"v":[[7.294,5.692],[-27.367,8.908],[-31.152,5.183],[-32.008,1.87],[-25.905,1.305],[19.931,-7.846],[31.56,-7.081],[30.079,-3.42]],"c":true},"ix":2},"nm":"Path 1","mn":"ADBE Vector Shape - Group","hd":false},{"ty":"fl","c":{"a":0,"k":[0.987999949736,0.451000019148,0.125,1],"ix":4},"o":{"a":0,"k":100,"ix":5},"r":1,"bm":0,"nm":"Fill 1","mn":"ADBE Vector Graphic - Fill","hd":false},{"ty":"tr","p":{"a":0,"k":[375.143,343.109],"ix":2},"a":{"a":0,"k":[0,0],"ix":1},"s":{"a":0,"k":[100,100],"ix":3},"r":{"a":0,"k":0,"ix":6},"o":{"a":0,"k":100,"ix":7},"sk":{"a":0,"k":0,"ix":4},"sa":{"a":0,"k":0,"ix":5},"nm":"Transform"}],"nm":"Group 21","np":4,"cix":2,"bm":0,"ix":21,"mn":"ADBE Vector Group","hd":false},{"ty":"gr","it":[{"ind":0,"ty":"sh","ix":1,"ks":{"a":0,"k":{"i":[[-2.622,3.135],[0.82,3.236],[-2.881,1.221],[-2.926,3.723],[0.756,5.429],[2.807,12.686],[4.718,3.972],[6.276,0.28],[0.198,0.468],[0.83,3.692],[5.61,0.009],[2.282,-4.369],[-1.051,-4.425],[0,0],[0,0],[-0.015,-7.619],[-2.938,-13.644],[-6.247,-4.978],[-5.744,-0.32],[0,0],[0,0],[0,0],[0,0],[-14.645,3.823]],"o":[[1.596,-1.871],[-1.359,-4.938],[4.05,-1.719],[3.377,-4.317],[-0.261,-1.913],[-5.332,-24.482],[-3.932,-3.203],[-3.255,-0.09],[-0.232,-0.545],[-1.834,-8.871],[-14.932,-0.099],[-0.426,0.731],[0,0],[0,0],[-10.221,5.806],[-0.027,1.667],[5.888,27.094],[4.407,3.461],[0,0],[0,0],[0,0],[0,0],[8.647,1.754],[9.941,-2.561]],"v":[[46.425,54.382],[47.303,48.22],[49.252,40.685],[64.549,28.865],[68.649,13.616],[63.071,-12.966],[51.438,-45.803],[31.91,-52.409],[25.682,-53.443],[23.811,-61.104],[15.548,-70.832],[-47.987,-55.092],[-46.801,-45.578],[-44.888,-37.384],[-51.331,-33.73],[-67.621,-12.116],[-62.302,15.588],[-49.419,49.64],[-28.64,57.46],[-24.597,57.675],[-22.851,63.091],[-21.216,68.463],[-16.798,69.346],[21.175,65.919]],"c":true},"ix":2},"nm":"Path 1","mn":"ADBE Vector Shape - Group","hd":false},{"ind":1,"ty":"sh","ix":2,"ks":{"a":0,"k":{"i":[[0.411,0.102],[3.27,-0.743],[3.512,-0.388],[0.136,-0.333],[0.198,0.467],[0.389,-0.165],[2.5,0.044],[0.279,-0.21],[2.218,0.898],[1.045,5.714],[1.878,-0.338],[0.198,0.467],[0.102,-0.41],[5.203,2.296],[2.765,12.796],[0.4,0.291],[-0.39,0.165],[1.593,4.839],[0.133,1.141],[0.686,0.536],[-0.152,0.343],[-0.063,0.06],[0.307,1.157],[-0.475,1.324],[0.166,0.39],[-4.548,4.227],[-2.237,1.225],[0,0],[0,0],[0.319,0.968],[-0.39,0.165],[0.333,0.135],[-2.296,2.169],[-17.898,3.088],[-3.649,-1.67],[-1.779,-5.495],[-0.229,-1.19],[-6.229,-1.033],[-3.932,-3.203],[-6.806,-31.208],[-0.016,-1.556],[3.726,-4.429],[0.278,-0.21],[0.192,-0.227],[1.024,-0.618],[1.749,-1.294],[1.852,-0.911],[-0.503,-2.268],[4.033,-3.274],[10.146,-4.029]],"o":[[-0.41,-0.101],[-3.19,0.71],[-3.545,0.308],[-0.136,0.333],[-0.232,-0.545],[-0.39,0.165],[-2.422,-0.076],[-0.279,0.21],[-4.137,-1.736],[-0.501,-2.913],[-1.112,0.196],[-0.198,-0.465],[-0.359,0.888],[-7.898,-3.451],[-0.786,-3.802],[-0.431,-0.368],[0.623,-0.264],[-0.383,-1.083],[-0.056,-2.733],[-0.344,-0.153],[0.036,-0.08],[0.356,-0.244],[-0.358,-1.36],[0.337,-1.154],[-0.516,-1.435],[2.376,-2.202],[0,0],[0,0],[-0.557,-2.613],[-0.429,-1.012],[0.389,-0.165],[-0.888,-0.359],[3.467,-3.309],[15.596,-2.665],[3.172,1.412],[1.022,3.058],[0.337,1.881],[7.205,1.171],[4.684,3.894],[3.56,16.411],[0.019,3.943],[-1.685,2.093],[-0.258,0.147],[-0.089,0.221],[-1.025,0.618],[-1.611,1.291],[-1.748,0.65],[1.505,7.448],[-2.92,2.433],[-7.121,2.927]],"v":[[20.542,74.827],[13.917,75.892],[1.701,77.858],[-4.935,79.111],[-5.523,78.809],[-6.62,78.171],[-11.865,78.372],[-16.81,78.632],[-21.315,77.326],[-27.503,68.372],[-30.092,65.519],[-32.523,64.987],[-33.122,64.874],[-51.179,60.22],[-65.233,38.796],[-67.461,31.378],[-67.557,30.5],[-71.419,11],[-72.195,7.653],[-76.199,-8.936],[-76.545,-9.834],[-76.395,-10.047],[-76.307,-12.658],[-76.126,-16.779],[-75.794,-19.677],[-66.312,-33.073],[-57.955,-39.375],[-53.98,-41.704],[-54.895,-46.462],[-56.46,-52.967],[-56.441,-55.089],[-56.406,-55.655],[-52.894,-62.108],[-5.572,-76.207],[23.906,-77.774],[29.035,-70.667],[31.317,-62.905],[38.77,-59.634],[58.194,-51.974],[71.013,-12.657],[77.58,19.94],[71.486,33.737],[67.926,37.912],[67.246,38.476],[65.264,39.868],[60.308,43.35],[55.097,46.663],[53.551,50.168],[50.898,61.678],[34.237,69.849]],"c":true},"ix":2},"nm":"Path 2","mn":"ADBE Vector Shape - Group","hd":false},{"ty":"mm","mm":1,"nm":"Merge Paths 1","mn":"ADBE Vector Filter - Merge","hd":false},{"ty":"fl","c":{"a":0,"k":[0.987999949736,0.451000019148,0.125,1],"ix":4},"o":{"a":0,"k":100,"ix":5},"r":1,"bm":0,"nm":"Fill 1","mn":"ADBE Vector Graphic - Fill","hd":false},{"ty":"tr","p":{"a":0,"k":[363.303,286.609],"ix":2},"a":{"a":0,"k":[0,0],"ix":1},"s":{"a":0,"k":[100,100],"ix":3},"r":{"a":0,"k":0,"ix":6},"o":{"a":0,"k":100,"ix":7},"sk":{"a":0,"k":0,"ix":4},"sa":{"a":0,"k":0,"ix":5},"nm":"Transform"}],"nm":"Group 22","np":6,"cix":2,"bm":0,"ix":22,"mn":"ADBE Vector Group","hd":false},{"ty":"gr","it":[{"ind":0,"ty":"sh","ix":1,"ks":{"a":0,"k":{"i":[[12.487,-3.275],[-13.913,4.247],[-2.486,-0.876]],"o":[[-19.46,5.039],[14.258,-4.303],[1.442,0.583]],"v":[[16.463,-1.843],[-17.628,3.153],[30.1,-6.524]],"c":true},"ix":2},"nm":"Path 1","mn":"ADBE Vector Shape - Group","hd":false},{"ty":"fl","c":{"a":0,"k":[0.328999986836,0.250999989229,0.136999990426,1],"ix":4},"o":{"a":0,"k":100,"ix":5},"r":1,"bm":0,"nm":"Fill 1","mn":"ADBE Vector Graphic - Fill","hd":false},{"ty":"tr","p":{"a":0,"k":[345.458,226.457],"ix":2},"a":{"a":0,"k":[0,0],"ix":1},"s":{"a":0,"k":[100,100],"ix":3},"r":{"a":0,"k":0,"ix":6},"o":{"a":0,"k":100,"ix":7},"sk":{"a":0,"k":0,"ix":4},"sa":{"a":0,"k":0,"ix":5},"nm":"Transform"}],"nm":"Group 23","np":4,"cix":2,"bm":0,"ix":23,"mn":"ADBE Vector Group","hd":false},{"ty":"gr","it":[{"ind":0,"ty":"sh","ix":1,"ks":{"a":0,"k":{"i":[[5.268,-1.449],[2.725,1.876],[-0.36,0.887],[-3.622,0.342],[-8.334,3.536],[-0.399,-0.29],[-0.065,-3.188],[7.2,-2.96]],"o":[[-15.257,3.898],[-0.798,-0.581],[0.089,-0.222],[12.157,-1.021],[1.635,-0.693],[0.875,0.548],[-0.007,1.933],[-5.076,2.021]],"v":[[9.671,8.012],[-29.271,12.401],[-32.478,-0.575],[-25.743,-1.595],[26.391,-13.234],[30.115,-13.987],[32.838,-2.368],[25.198,2.803]],"c":true},"ix":2},"nm":"Path 1","mn":"ADBE Vector Shape - Group","hd":false},{"ty":"fl","c":{"a":0,"k":[0.328999986836,0.250999989229,0.136999990426,1],"ix":4},"o":{"a":0,"k":100,"ix":5},"r":1,"bm":0,"nm":"Fill 1","mn":"ADBE Vector Graphic - Fill","hd":false},{"ty":"tr","p":{"a":0,"k":[351.954,236.486],"ix":2},"a":{"a":0,"k":[0,0],"ix":1},"s":{"a":0,"k":[100,100],"ix":3},"r":{"a":0,"k":0,"ix":6},"o":{"a":0,"k":100,"ix":7},"sk":{"a":0,"k":0,"ix":4},"sa":{"a":0,"k":0,"ix":5},"nm":"Transform"}],"nm":"Group 24","np":4,"cix":2,"bm":0,"ix":24,"mn":"ADBE Vector Group","hd":false},{"ty":"gr","it":[{"ind":0,"ty":"sh","ix":1,"ks":{"a":0,"k":{"i":[[7.864,-2.693],[10.071,-1.608],[1.737,1.928],[-4.597,-0.439],[-16.01,6.883],[-5.254,-0.252],[2.297,-2.169]],"o":[[-6.384,2.065],[-15.55,2.553],[-1.593,-1.806],[12.439,1.156],[7.444,-3.249],[6.92,0.281],[-1.57,1.493]],"v":[[25.274,0.15],[-13.452,8.951],[-46.127,10.129],[-29.859,2.768],[25.738,-8.501],[39.592,-11.806],[45.424,-8.673]],"c":true},"ix":2},"nm":"Path 1","mn":"ADBE Vector Shape - Group","hd":false},{"ty":"fl","c":{"a":0,"k":[0.328999986836,0.250999989229,0.136999990426,1],"ix":4},"o":{"a":0,"k":100,"ix":5},"r":1,"bm":0,"nm":"Fill 1","mn":"ADBE Vector Graphic - Fill","hd":false},{"ty":"tr","p":{"a":0,"k":[354.904,250.171],"ix":2},"a":{"a":0,"k":[0,0],"ix":1},"s":{"a":0,"k":[100,100],"ix":3},"r":{"a":0,"k":0,"ix":6},"o":{"a":0,"k":100,"ix":7},"sk":{"a":0,"k":0,"ix":4},"sa":{"a":0,"k":0,"ix":5},"nm":"Transform"}],"nm":"Group 25","np":4,"cix":2,"bm":0,"ix":25,"mn":"ADBE Vector Group","hd":false},{"ty":"gr","it":[{"ind":0,"ty":"sh","ix":1,"ks":{"a":0,"k":{"i":[[2.884,1.166],[-0.643,2.385],[-1.687,-0.296],[0.986,-2.44]],"o":[[-2.551,-1.032],[0.462,-1.943],[2.365,0.375],[-1.166,2.884]],"v":[[-1.607,3.865],[-4.233,-0.81],[0.902,-4.735],[3.89,1.441]],"c":true},"ix":2},"nm":"Path 1","mn":"ADBE Vector Shape - Group","hd":false},{"ty":"fl","c":{"a":0,"k":[0.328999986836,0.250999989229,0.136999990426,1],"ix":4},"o":{"a":0,"k":100,"ix":5},"r":1,"bm":0,"nm":"Fill 1","mn":"ADBE Vector Graphic - Fill","hd":false},{"ty":"tr","p":{"a":0,"k":[340.937,285.566],"ix":2},"a":{"a":0,"k":[0,0],"ix":1},"s":{"a":0,"k":[100,100],"ix":3},"r":{"a":0,"k":0,"ix":6},"o":{"a":0,"k":100,"ix":7},"sk":{"a":0,"k":0,"ix":4},"sa":{"a":0,"k":0,"ix":5},"nm":"Transform"}],"nm":"Group 26","np":4,"cix":2,"bm":0,"ix":26,"mn":"ADBE Vector Group","hd":false},{"ty":"gr","it":[{"ind":0,"ty":"sh","ix":1,"ks":{"a":0,"k":{"i":[[2.662,1.076],[0.264,0.623],[-1.246,0.528],[2.269,-3.536]],"o":[[-1.222,-0.494],[-0.562,-1.324],[3.817,-1.619],[-1.598,2.516]],"v":[[-1.821,4.288],[-4.535,2.224],[-2.381,-3.746],[2.828,2.684]],"c":true},"ix":2},"nm":"Path 1","mn":"ADBE Vector Shape - Group","hd":false},{"ty":"fl","c":{"a":0,"k":[0.328999986836,0.250999989229,0.136999990426,1],"ix":4},"o":{"a":0,"k":100,"ix":5},"r":1,"bm":0,"nm":"Fill 1","mn":"ADBE Vector Graphic - Fill","hd":false},{"ty":"tr","p":{"a":0,"k":[384.956,275.75],"ix":2},"a":{"a":0,"k":[0,0],"ix":1},"s":{"a":0,"k":[100,100],"ix":3},"r":{"a":0,"k":0,"ix":6},"o":{"a":0,"k":100,"ix":7},"sk":{"a":0,"k":0,"ix":4},"sa":{"a":0,"k":0,"ix":5},"nm":"Transform"}],"nm":"Group 27","np":4,"cix":2,"bm":0,"ix":27,"mn":"ADBE Vector Group","hd":false},{"ty":"gr","it":[{"ind":0,"ty":"sh","ix":1,"ks":{"a":0,"k":{"i":[[5.838,-1.188],[7.2,-2.96],[0.444,0.18],[-0.461,1.298],[-3.623,0.341],[-7.395,1.85],[-0.516,-4.466]],"o":[[-2.268,0.502],[-7.121,2.928],[-0.809,-0.391],[0.135,-0.332],[9.679,-0.798],[7.159,-1.75],[0.411,3.134]],"v":[[14.402,-0.945],[-2.863,5.367],[-16.712,10.414],[-20.381,-3.652],[-13.478,-4.925],[11.788,-8.843],[20.43,-5.8]],"c":true},"ix":2},"nm":"Path 1","mn":"ADBE Vector Shape - Group","hd":false},{"ty":"fl","c":{"a":0,"k":[0.328999986836,0.250999989229,0.136999990426,1],"ix":4},"o":{"a":0,"k":100,"ix":5},"r":1,"bm":0,"nm":"Fill 1","mn":"ADBE Vector Graphic - Fill","hd":false},{"ty":"tr","p":{"a":0,"k":[369.478,316.324],"ix":2},"a":{"a":0,"k":[0,0],"ix":1},"s":{"a":0,"k":[100,100],"ix":3},"r":{"a":0,"k":0,"ix":6},"o":{"a":0,"k":100,"ix":7},"sk":{"a":0,"k":0,"ix":4},"sa":{"a":0,"k":0,"ix":5},"nm":"Transform"}],"nm":"Group 28","np":4,"cix":2,"bm":0,"ix":28,"mn":"ADBE Vector Group","hd":false},{"ty":"gr","it":[{"ind":0,"ty":"sh","ix":1,"ks":{"a":0,"k":{"i":[[-3.729,7.463],[0.679,2.469],[-1.393,1.05],[3.545,-0.309],[3.131,0.429],[-0.265,-0.623],[-2.551,-1.032],[0.458,-0.653],[-0.004,-1.743]],"o":[[0.919,-1.952],[-0.799,-2.969],[1.55,-1.118],[-3.156,0.161],[-5.119,-0.585],[0.065,0.156],[2.995,1.21],[-0.368,0.432],[0.123,8.311]],"v":[[-15.773,-1.835],[-15.417,-8.144],[-14.732,-13.029],[-16.951,-13.926],[-26.403,-14.328],[-39.066,-14.286],[-34.277,-12.09],[-30.321,-9.266],[-30.992,-5.213]],"c":true},"ix":2},"nm":"Path 1","mn":"ADBE Vector Shape - Group","hd":false},{"ind":1,"ty":"sh","ix":2,"ks":{"a":0,"k":{"i":[[-0.54,1.332],[2.885,1.166],[-2.796,2.29],[7.977,-3.293],[-0.866,-0.093],[0.675,-2.308],[-4.103,-1.659],[-2.639,1.579]],"o":[[1.211,-2.994],[-1.884,-0.763],[2.786,-2.101],[-5.219,2.214],[1.166,0.149],[-1.06,4.218],[2.995,1.211],[1.612,-0.96]],"v":[[28.422,-12.037],[24.46,-22.027],[25.415,-25.19],[19.801,-23.911],[12.589,-20.116],[13.155,-17.048],[18.051,-7.454],[24.486,-7.885]],"c":true},"ix":2},"nm":"Path 2","mn":"ADBE Vector Shape - Group","hd":false},{"ind":2,"ty":"sh","ix":3,"ks":{"a":0,"k":{"i":[[0,0],[0.683,-1.209],[-1.402,0.595],[0.363,0.856]],"o":[[-0.595,-1.402],[-0.771,1.43],[0.39,-0.166],[0,0]],"v":[[-43.391,27.525],[-44.857,27.32],[-43.398,29.458],[-43.39,27.525]],"c":true},"ix":2},"nm":"Path 3","mn":"ADBE Vector Shape - Group","hd":false},{"ind":3,"ty":"sh","ix":4,"ks":{"a":0,"k":{"i":[[0,0],[0.496,-0.386],[-0.058,-0.405],[-0.7,0.297],[0.354,0.401]],"o":[[-0.385,-0.497],[-0.324,0.25],[0.043,0.533],[0.701,-0.298],[0,0]],"v":[[-30.873,24.972],[-32.469,24.771],[-32.898,25.831],[-31.522,26.259],[-30.872,24.972]],"c":true},"ix":2},"nm":"Path 4","mn":"ADBE Vector Shape - Group","hd":false},{"ind":4,"ty":"sh","ix":5,"ks":{"a":0,"k":{"i":[[0,0],[0.39,-0.165],[-0.888,-0.357],[0.496,1.168]],"o":[[-0.264,-0.624],[-1.013,0.429],[1.222,0.494],[0,0]],"v":[[-23.958,23.509],[-25.154,22.638],[-25.452,24.969],[-23.957,23.509]],"c":true},"ix":2},"nm":"Path 5","mn":"ADBE Vector Shape - Group","hd":false},{"ind":5,"ty":"sh","ix":6,"ks":{"a":0,"k":{"i":[[0,0],[0.467,-0.197],[-0.265,-0.623],[-0.389,0.165],[0.264,0.624]],"o":[[-0.265,-0.624],[-0.389,0.166],[0.264,0.623],[0.467,-0.198],[0,0]],"v":[[-35.427,31.132],[-36.702,30.293],[-36.985,31.792],[-35.711,32.63],[-35.427,31.131]],"c":true},"ix":2},"nm":"Path 6","mn":"ADBE Vector Shape - Group","hd":false},{"ind":6,"ty":"sh","ix":7,"ks":{"a":0,"k":{"i":[[1.666,9.127],[1.782,-1.215],[-2.322,-11.972],[-0.386,-0.479],[-0.458,0.478]],"o":[[-3.117,-16.231],[-0.946,0.585],[1.636,8.405],[0.502,0.432],[0.602,-0.531]],"v":[[50.507,-18.464],[45.048,-35.448],[46.778,-19.456],[50.507,-3.3],[52.218,-3.383]],"c":true},"ix":2},"nm":"Path 7","mn":"ADBE Vector Shape - Group","hd":false},{"ind":7,"ty":"sh","ix":8,"ks":{"a":0,"k":{"i":[[0,0],[0.496,-0.386],[-0.057,-0.406],[-0.7,0.297],[0.354,0.401]],"o":[[-0.386,-0.496],[-0.323,0.251],[0.043,0.533],[0.701,-0.297],[0,0]],"v":[[-41.135,37.597],[-42.732,37.396],[-43.161,38.457],[-41.785,38.884],[-41.139,37.598]],"c":true},"ix":2},"nm":"Path 8","mn":"ADBE Vector Shape - Group","hd":false},{"ind":8,"ty":"sh","ix":9,"ks":{"a":0,"k":{"i":[[0,0],[0.389,-0.165],[-0.888,-0.359],[0.496,1.169]],"o":[[-0.264,-0.623],[-1.013,0.429],[1.215,0.495],[0,0]],"v":[[-21.877,32.736],[-23.073,31.865],[-23.371,34.197],[-21.88,32.737]],"c":true},"ix":2},"nm":"Path 9","mn":"ADBE Vector Shape - Group","hd":false},{"ind":9,"ty":"sh","ix":10,"ks":{"a":0,"k":{"i":[[0,0],[-0.562,-1.324],[-0.684,0.279],[-0.011,0.004],[0.387,0.479]],"o":[[-1.061,-1.204],[0.279,0.683],[0.011,-0.005],[0.697,-0.297],[0,0]],"v":[[34.805,10.805],[32.493,11.418],[34.236,12.15],[34.267,12.136],[34.802,10.806]],"c":true},"ix":2},"nm":"Path 10","mn":"ADBE Vector Shape - Group","hd":false},{"ind":10,"ty":"sh","ix":11,"ks":{"a":0,"k":{"i":[[0,0],[0.389,-0.165],[-0.888,-0.358],[0.497,1.17]],"o":[[-0.264,-0.623],[-1.013,0.43],[1.217,0.494],[0,0]],"v":[[41.753,9.419],[40.557,8.548],[40.259,10.88],[41.75,9.42]],"c":true},"ix":2},"nm":"Path 11","mn":"ADBE Vector Shape - Group","hd":false},{"ind":11,"ty":"sh","ix":12,"ks":{"a":0,"k":{"i":[[0,0],[1.214,-1.251],[-0.433,-0.368],[-0.161,1.354]],"o":[[0.283,-1.5],[-0.603,0.53],[1.05,0.749],[0,0]],"v":[[-27.493,40.082],[-29.546,39.574],[-29.796,41.15],[-27.495,40.082]],"c":true},"ix":2},"nm":"Path 12","mn":"ADBE Vector Shape - Group","hd":false},{"ind":12,"ty":"sh","ix":13,"ks":{"a":0,"k":{"i":[[0,0],[2.102,-0.892],[-0.974,-0.781],[0.1,3.265]],"o":[[-0.042,-3.566],[-0.935,0.396],[1.562,1.084],[0,0]],"v":[[54.568,4.535],[51.228,0.346],[52.008,8.469],[54.566,4.536]],"c":true},"ix":2},"nm":"Path 13","mn":"ADBE Vector Shape - Group","hd":false},{"ind":13,"ty":"sh","ix":14,"ks":{"a":0,"k":{"i":[[0,0],[0.497,-0.386],[-0.058,-0.405],[-0.701,0.297],[0.354,0.401]],"o":[[-0.385,-0.496],[-0.323,0.251],[0.043,0.532],[0.7,-0.297],[0,0]],"v":[[48.383,12.489],[46.787,12.288],[46.358,13.348],[47.735,13.776],[48.382,12.489]],"c":true},"ix":2},"nm":"Path 14","mn":"ADBE Vector Shape - Group","hd":false},{"ind":14,"ty":"sh","ix":15,"ks":{"a":0,"k":{"i":[[0.561,1.324],[0.614,-0.285],[-1.332,-0.538]],"o":[[-0.287,-0.614],[-1.169,0.496],[1.075,0.371]],"v":[[36.904,19.656],[35.273,19.061],[35.662,21.929]],"c":true},"ix":2},"nm":"Path 15","mn":"ADBE Vector Shape - Group","hd":false},{"ind":15,"ty":"sh","ix":16,"ks":{"a":0,"k":{"i":[[0,0],[0.5,2.913],[11.328,-2.324],[8.474,0.264],[1.073,-0.796],[-0.609,-3.601],[-1.06,-3.194],[-18.98,7.684],[-1.444,0.062],[-0.079,0.033],[-0.806,1.352]],"o":[[1.094,-1.751],[-1.188,-6.481],[-14.943,3.123],[-1.337,-0.013],[-1.471,1.083],[0.654,3.301],[2.714,8.131],[8.523,-3.524],[1.521,-0.095],[0.192,0.01],[0,0]],"v":[[28.862,24.537],[29.653,17.952],[15.24,13.221],[-13.712,16.681],[-17.427,17.889],[-18.393,23.629],[-15.818,33.381],[5.876,33.828],[24.064,27.307],[26.997,27.075],[28.865,24.537]],"c":true},"ix":2},"nm":"Path 16","mn":"ADBE Vector Shape - Group","hd":false},{"ind":16,"ty":"sh","ix":17,"ks":{"a":0,"k":{"i":[[0,0],[0.496,-0.386],[-0.058,-0.404],[-0.701,0.297],[0.354,0.4]],"o":[[-0.386,-0.497],[-0.323,0.251],[0.043,0.533],[0.701,-0.298],[0,0]],"v":[[56.477,16.407],[54.879,16.206],[54.451,17.265],[55.827,17.694],[56.477,16.408]],"c":true},"ix":2},"nm":"Path 17","mn":"ADBE Vector Shape - Group","hd":false},{"ind":17,"ty":"sh","ix":18,"ks":{"a":0,"k":{"i":[[0,0],[0.767,-0.144],[-0.33,-0.778],[0.36,1.501]],"o":[[-0.087,-0.423],[-0.923,0.208],[0.563,1.324],[0,0]],"v":[[45.262,23.553],[43.664,23.037],[42.692,24.643],[45.264,23.553]],"c":true},"ix":2},"nm":"Path 18","mn":"ADBE Vector Shape - Group","hd":false},{"ind":18,"ty":"sh","ix":19,"ks":{"a":0,"k":{"i":[[1.547,-0.472],[12.551,0.558],[3.178,15.288],[1.977,8.994],[-2.509,5.568],[-2.215,-1.542],[-18.753,3.452],[-5.797,5.4],[0,0],[0,0],[-2.568,-11.685],[1.025,-3.651],[6.783,-4.809],[8.756,-3.622]],"o":[[-13.48,3.972],[-18.827,-0.836],[-0.544,-2.8],[-5.105,-22.648],[2.297,-5.201],[3.445,2.489],[24.892,-4.583],[0,0],[0,0],[5.567,2.509],[8.207,36.68],[-1.687,5.771],[-4.879,3.448],[-6.261,2.563]],"v":[[22.117,43.298],[-26.276,49.673],[-55.128,28.46],[-59.814,7.014],[-62.525,-22.991],[-56.898,-27.491],[-16.833,-29.232],[39.659,-47.498],[42.634,-50.231],[45.728,-48.786],[55.576,-31.642],[64.008,15.97],[54.008,28.576],[36.3,37.742]],"c":true},"ix":2},"nm":"Path 19","mn":"ADBE Vector Shape - Group","hd":false},{"ty":"mm","mm":1,"nm":"Merge Paths 1","mn":"ADBE Vector Filter - Merge","hd":false},{"ty":"fl","c":{"a":0,"k":[0.328999986836,0.250999989229,0.136999990426,1],"ix":4},"o":{"a":0,"k":100,"ix":5},"r":1,"bm":0,"nm":"Fill 1","mn":"ADBE Vector Graphic - Fill","hd":false},{"ty":"tr","p":{"a":0,"k":[363.805,290.974],"ix":2},"a":{"a":0,"k":[0,0],"ix":1},"s":{"a":0,"k":[100,100],"ix":3},"r":{"a":0,"k":0,"ix":6},"o":{"a":0,"k":100,"ix":7},"sk":{"a":0,"k":0,"ix":4},"sa":{"a":0,"k":0,"ix":5},"nm":"Transform"}],"nm":"Group 29","np":23,"cix":2,"bm":0,"ix":29,"mn":"ADBE Vector Group","hd":false},{"ty":"gr","it":[{"ind":0,"ty":"sh","ix":1,"ks":{"a":0,"k":{"i":[[6.96,-1.574],[3.97,1.993],[-1.013,0.43],[-5.067,0.403],[-12.112,3.944],[-1.553,-3.66],[1.859,-1.248]],"o":[[-12.731,2.919],[-1.431,-0.772],[0.39,-0.166],[11.357,-0.958],[10.133,-3.195],[0.76,1.792],[-3.921,2.674]],"v":[[4.223,6.971],[-29.322,8.702],[-31.606,1.583],[-21.727,0.609],[17.751,-7.499],[31.859,-6.959],[30.568,-3.286]],"c":true},"ix":2},"nm":"Path 1","mn":"ADBE Vector Shape - Group","hd":false},{"ty":"fl","c":{"a":0,"k":[0.328999986836,0.250999989229,0.136999990426,1],"ix":4},"o":{"a":0,"k":100,"ix":5},"r":1,"bm":0,"nm":"Fill 1","mn":"ADBE Vector Graphic - Fill","hd":false},{"ty":"tr","p":{"a":0,"k":[375.065,343.074],"ix":2},"a":{"a":0,"k":[0,0],"ix":1},"s":{"a":0,"k":[100,100],"ix":3},"r":{"a":0,"k":0,"ix":6},"o":{"a":0,"k":100,"ix":7},"sk":{"a":0,"k":0,"ix":4},"sa":{"a":0,"k":0,"ix":5},"nm":"Transform"}],"nm":"Group 30","np":4,"cix":2,"bm":0,"ix":30,"mn":"ADBE Vector Group","hd":false},{"ty":"gr","it":[{"ind":0,"ty":"sh","ix":1,"ks":{"a":0,"k":{"i":[[-3.386,2.631],[0.772,4.635],[-0.491,0.576],[-3.964,2.785],[-0.434,6.342],[2.652,9.719],[0.546,2.801],[8.282,4.575],[4.69,-0.428],[0.46,4.766],[1.014,1.959],[18.344,-4.199],[8.52,-2.878],[-2.284,-10.151],[0.413,-0.543],[1.948,-0.826],[1.394,-7.115],[-2.587,-9.562],[-0.632,-3.223],[-9.259,-4.71],[-4.153,-0.26],[-0.055,-0.344],[-0.714,-2.547],[-10.228,-0.715],[-7.385,2.306],[-1.736,0.46]],"o":[[2.797,-2.289],[-0.445,-2.568],[0.491,-0.576],[9.556,-6.719],[0.338,-4.187],[-0.472,-1.546],[-2.981,-17.208],[-4.545,-2.483],[-1.947,0.182],[-0.235,-2.289],[-1.158,-2.082],[-13.465,3.138],[-9.535,3.31],[0.996,4.081],[-0.38,0.621],[-8.166,3.281],[-0.668,3.408],[0.406,1.391],[4.927,25.478],[4.192,2.083],[1.622,0.14],[0.054,0.345],[1.589,5.483],[7.664,0.517],[2.28,-0.691],[4.847,-1.137]],"v":[[44.842,55.421],[46.956,48.275],[47.089,42.521],[55.243,36.397],[68.248,19.392],[62.757,-12.833],[61.021,-20.827],[46.879,-48.096],[27.243,-52.357],[24.298,-57.999],[20.853,-69.587],[-17.054,-65.359],[-38.884,-59.409],[-46.524,-45.139],[-45.5,-36.659],[-49.753,-34.12],[-67.042,-15.298],[-63.54,8.121],[-61.716,16.538],[-44.918,52.234],[-27.008,57.41],[-24.066,58.277],[-22.685,63.482],[-10.756,69.724],[18.152,66.376],[25.403,64.404]],"c":true},"ix":2},"nm":"Path 1","mn":"ADBE Vector Shape - Group","hd":false},{"ind":1,"ty":"sh","ix":2,"ks":{"a":0,"k":{"i":[[0.411,0.102],[3.27,-0.743],[3.512,-0.388],[0.136,-0.333],[0.198,0.466],[0.389,-0.165],[2.5,0.044],[0.279,-0.21],[2.218,0.898],[1.045,5.714],[1.878,-0.338],[0.198,0.467],[0.102,-0.41],[5.203,2.296],[2.765,12.796],[0.4,0.291],[-0.39,0.165],[1.593,4.839],[0.133,1.141],[0.687,0.536],[-0.152,0.343],[-0.063,0.06],[0.307,1.157],[-0.475,1.324],[0.166,0.39],[-4.548,4.227],[-2.237,1.225],[0,0],[0,0],[0.319,0.968],[-0.39,0.165],[0.333,0.135],[-2.296,2.169],[-17.898,3.087],[-3.649,-1.67],[-1.779,-5.495],[-0.229,-1.19],[-6.229,-1.033],[-3.932,-3.202],[-6.806,-31.208],[-0.016,-1.556],[3.726,-4.429],[0.278,-0.21],[0.192,-0.227],[1.024,-0.618],[1.749,-1.294],[1.852,-0.911],[-0.503,-2.268],[4.033,-3.274],[10.146,-4.03]],"o":[[-0.41,-0.101],[-3.19,0.71],[-3.545,0.308],[-0.136,0.333],[-0.232,-0.545],[-0.39,0.165],[-2.422,-0.076],[-0.279,0.21],[-4.137,-1.736],[-0.501,-2.913],[-1.112,0.196],[-0.198,-0.465],[-0.359,0.888],[-7.898,-3.451],[-0.786,-3.802],[-0.431,-0.368],[0.623,-0.265],[-0.383,-1.083],[-0.056,-2.733],[-0.344,-0.153],[0.036,-0.08],[0.356,-0.244],[-0.358,-1.36],[0.337,-1.154],[-0.516,-1.435],[2.376,-2.202],[0,0],[0,0],[-0.557,-2.613],[-0.429,-1.012],[0.389,-0.165],[-0.888,-0.359],[3.467,-3.309],[15.596,-2.665],[3.172,1.412],[1.022,3.058],[0.337,1.881],[7.205,1.171],[4.684,3.895],[3.56,16.411],[0.019,3.943],[-1.685,2.093],[-0.258,0.147],[-0.089,0.221],[-1.025,0.618],[-1.611,1.291],[-1.748,0.65],[1.505,7.448],[-2.92,2.432],[-7.121,2.926]],"v":[[20.542,74.827],[13.917,75.892],[1.701,77.858],[-4.935,79.11],[-5.523,78.809],[-6.62,78.171],[-11.865,78.372],[-16.81,78.633],[-21.315,77.326],[-27.503,68.372],[-30.092,65.519],[-32.523,64.987],[-33.122,64.874],[-51.179,60.22],[-65.233,38.796],[-67.461,31.378],[-67.557,30.5],[-71.419,11.001],[-72.195,7.654],[-76.199,-8.936],[-76.545,-9.833],[-76.395,-10.047],[-76.307,-12.658],[-76.126,-16.779],[-75.794,-19.677],[-66.312,-33.073],[-57.955,-39.375],[-53.98,-41.704],[-54.895,-46.462],[-56.46,-52.967],[-56.441,-55.089],[-56.406,-55.655],[-52.894,-62.108],[-5.572,-76.207],[23.906,-77.774],[29.035,-70.667],[31.317,-62.905],[38.77,-59.634],[58.194,-51.975],[71.013,-12.657],[77.58,19.94],[71.486,33.737],[67.926,37.913],[67.246,38.477],[65.264,39.868],[60.308,43.35],[55.097,46.663],[53.551,50.168],[50.898,61.678],[34.237,69.849]],"c":true},"ix":2},"nm":"Path 2","mn":"ADBE Vector Shape - Group","hd":false},{"ty":"mm","mm":1,"nm":"Merge Paths 1","mn":"ADBE Vector Filter - Merge","hd":false},{"ty":"fl","c":{"a":0,"k":[0.328999986836,0.250999989229,0.136999990426,1],"ix":4},"o":{"a":0,"k":100,"ix":5},"r":1,"bm":0,"nm":"Fill 1","mn":"ADBE Vector Graphic - Fill","hd":false},{"ty":"tr","p":{"a":0,"k":[363.303,286.609],"ix":2},"a":{"a":0,"k":[0,0],"ix":1},"s":{"a":0,"k":[100,100],"ix":3},"r":{"a":0,"k":0,"ix":6},"o":{"a":0,"k":100,"ix":7},"sk":{"a":0,"k":0,"ix":4},"sa":{"a":0,"k":0,"ix":5},"nm":"Transform"}],"nm":"Group 31","np":6,"cix":2,"bm":0,"ix":31,"mn":"ADBE Vector Group","hd":false},{"ty":"gr","it":[{"ind":0,"ty":"sh","ix":1,"ks":{"a":0,"k":{"i":[[0.411,0.102],[3.27,-0.743],[3.512,-0.387],[0.137,-0.333],[0.198,0.467],[0.389,-0.165],[2.5,0.044],[0.28,-0.21],[2.217,0.897],[1.045,5.714],[1.878,-0.337],[0.198,0.467],[0.101,-0.41],[5.203,2.295],[2.765,12.796],[0.399,0.291],[-0.389,0.165],[1.593,4.839],[0.133,1.141],[0.686,0.535],[-0.152,0.344],[-0.062,0.061],[0.308,1.156],[-0.476,1.324],[0.166,0.389],[-4.548,4.227],[-2.237,1.224],[0,0],[0,0],[0.318,0.967],[-0.39,0.165],[0.333,0.134],[-2.295,2.17],[-17.898,3.088],[-3.649,-1.67],[-1.779,-5.494],[-0.228,-1.19],[-6.229,-1.034],[-3.931,-3.202],[-6.806,-31.208],[-0.017,-1.555],[3.727,-4.43],[0.278,-0.21],[0.192,-0.226],[1.024,-0.618],[1.749,-1.293],[1.852,-0.911],[-0.503,-2.269],[4.034,-3.274],[10.147,-4.029]],"o":[[-0.41,-0.102],[-3.19,0.71],[-3.545,0.309],[-0.135,0.333],[-0.232,-0.544],[-0.39,0.165],[-2.422,-0.076],[-0.278,0.21],[-4.137,-1.736],[-0.501,-2.913],[-1.112,0.197],[-0.198,-0.466],[-0.359,0.888],[-7.897,-3.452],[-0.787,-3.802],[-0.432,-0.368],[0.623,-0.265],[-0.383,-1.083],[-0.056,-2.733],[-0.344,-0.153],[0.036,-0.08],[0.357,-0.243],[-0.357,-1.36],[0.337,-1.155],[-0.517,-1.435],[2.375,-2.203],[0,0],[0,0],[-0.556,-2.612],[-0.43,-1.013],[0.389,-0.165],[-0.888,-0.359],[3.468,-3.308],[15.595,-2.664],[3.172,1.412],[1.022,3.059],[0.338,1.88],[7.205,1.171],[4.685,3.895],[3.56,16.411],[0.019,3.944],[-1.684,2.093],[-0.258,0.146],[-0.089,0.222],[-1.025,0.618],[-1.611,1.291],[-1.748,0.649],[1.505,7.448],[-2.919,2.432],[-7.12,2.927]],"v":[[20.542,74.827],[13.917,75.891],[1.701,77.857],[-4.936,79.11],[-5.523,78.808],[-6.62,78.172],[-11.865,78.372],[-16.811,78.633],[-21.315,77.326],[-27.503,68.372],[-30.092,65.518],[-32.523,64.987],[-33.122,64.875],[-51.18,60.22],[-65.233,38.797],[-67.461,31.379],[-67.558,30.5],[-71.419,11.001],[-72.195,7.654],[-76.199,-8.936],[-76.545,-9.835],[-76.396,-10.048],[-76.308,-12.658],[-76.126,-16.779],[-75.794,-19.677],[-66.312,-33.073],[-57.955,-39.375],[-53.98,-41.704],[-54.896,-46.462],[-56.46,-52.966],[-56.441,-55.089],[-56.406,-55.655],[-52.895,-62.109],[-5.572,-76.208],[23.906,-77.773],[29.035,-70.668],[31.316,-62.905],[38.77,-59.634],[58.193,-51.975],[71.013,-12.656],[77.58,19.939],[71.485,33.737],[67.926,37.913],[67.246,38.475],[65.264,39.868],[60.308,43.349],[55.097,46.664],[53.551,50.168],[50.897,61.678],[34.236,69.849]],"c":true},"ix":2},"nm":"Path 1","mn":"ADBE Vector Shape - Group","hd":false},{"ty":"fl","c":{"a":0,"k":[0.122000002394,0.071000005685,0.004000000393,1],"ix":4},"o":{"a":0,"k":100,"ix":5},"r":1,"bm":0,"nm":"Fill 1","mn":"ADBE Vector Graphic - Fill","hd":false},{"ty":"tr","p":{"a":0,"k":[363.303,286.609],"ix":2},"a":{"a":0,"k":[0,0],"ix":1},"s":{"a":0,"k":[100,100],"ix":3},"r":{"a":0,"k":0,"ix":6},"o":{"a":0,"k":100,"ix":7},"sk":{"a":0,"k":0,"ix":4},"sa":{"a":0,"k":0,"ix":5},"nm":"Transform"}],"nm":"Group 32","np":4,"cix":2,"bm":0,"ix":32,"mn":"ADBE Vector Group","hd":false}],"ip":0,"op":44.0000017921567,"st":0,"bm":0}],"markers":[]}